Workbook

Sheet sheet1
A1: SPUID | B1: 商品标题 | C1: 商品货号 | D1: 品牌名称 | E1: 类目名称 | F1: 商品类型 | G1: 出价渠道 | H1: 支付金额 | I1: 6 | J1: 7 | K1: 8 | L1: 9 | M1: 10 | N1: 11 | O1: 总 | P1: 总 | Q1: 支付订单数 | R1: 商详访问人数 | S1: 商详转化率 | T1: 收藏用户数 | U1: 我的销量 | V1: 退货金额（退款时间） | W1: 退货订单数（退款时间） | X1: 退货金额（支付时间） | Y1: 退货订单数（支付时间） | Z1: 我的出价（元） | AA1: 平台最低价（元） | AB1: 当前单品收入 | AC1: 当前单品利润 | AD1: 支付笔单价 | AE1: 支付用户数 | AF1: 商家成本价 | AG1: 当前整体收入 | AH1: 当前整体利润 | AI1: 最低价-预估单品收入 | AJ1: 最低价-预估单品利润 | AK1: 最低价-预估整体收入 | AL1: 最低价-预估整体利润 | AM1: 商详访问次数 | AN1: 支付品牌新客比率 | AO1: 支付Z世代客比率 | AP1: 商详品牌新客比率 | AQ1: 商详Z世代客比率 | AR1: 收藏品牌新客比率 | AS1: 收藏Z世代客比率 | AT1: 好评订单数 | AU1: 中差评订单数 | AV1: 好评率 | AW1: 品质投诉订单数 | AX1: 品质退款订单数
A2: 9477032 | B2: 伯希和PELLIOT 经典1.0 户外夏季速干短袖超轻抗皱翻领运动半袖吸湿散热徒步登山跑步衣透气抑菌凉感Polo衫 男款 | C2: 11421507 | D2: 伯希和/PELLIOT | E2: 服装-上衣-Polo衫 | F2: 一品多商 | G2: 品牌直发 | H2: 8557.47 | I2: =VLOOKUP(C2,[6]sheet1!$C:$X,6,0) -> 4329 | J2: =VLOOKUP(C2,[1]sheet1!$C:$I,6,0) -> 8037 | K2: =VLOOKUP(C2,[2]sheet1!$C:$H,6,0) -> 4640 | L2: =VLOOKUP(C2,[3]sheet1!$C:$H,6,0) -> 3862 | M2: =VLOOKUP(C2,[4]sheet1!$C:$I,6,0) -> 6959 | N2: =VLOOKUP(C2,[5]sheet1!$C:$J,6,0) -> 6257 | O2: =H2+I2+J2+K2+L2+M2+N2 -> 42641.47 | P2: 42641.47 | Q2: 69 | R2: 3309 | S2: 327 | T2: 415 | U2: 69 | V2: 821 | W2: 7 | X2: 1259.51 | Y2: 9 | Z2: 163-196 | AA2: 154 | AB2: 133.07 | AC2: - | AD2: 124.02 | AE2: 64 | AF2: - | AG2: 9181.83 | AH2: - | AI2: 136.04 | AJ2: - | AK2: 9386.76 | AL2: - | AM2: 3902 | AN2: 0.75 | AO2: 0.5 | AP2: 0.8605 | AQ2: 0.3993 | AR2: 0.8723 | AS2: 0.4651 | AT2: 1 | AU2: 0 | AV2: 1 | AW2: 0 | AX2: 0
A3: 8298814 | B3: 伯希和PELLIOT 小森林皮肤衣轻量化户外骑行宽松冰凉降温强劲轻薄凉感透气防紫外线UPF50+ 多巴胺连帽防晒服 男女同款 | C3: 12421220 | D3: 伯希和/PELLIOT | E3: 服装-外套-防晒服 | F3: 一品多商 | G3: 品牌直发 | H3: 14794 | I3: =VLOOKUP(C3,[6]sheet1!$C:$X,6,0) -> 20578 | J3: =VLOOKUP(C3,[1]sheet1!$C:$I,6,0) -> 24810.93 | K3: =VLOOKUP(C3,[2]sheet1!$C:$H,6,0) -> 22371 | L3: =VLOOKUP(C3,[3]sheet1!$C:$H,6,0) -> 20698.46 | M3: =VLOOKUP(C3,[4]sheet1!$C:$I,6,0) -> 15783.72 | N3: =VLOOKUP(C3,[5]sheet1!$C:$J,6,0) -> 12303.86 | O3: =H3+I3+J3+K3+L3+M3+N3 -> 131339.97 | P3: 131339.97 | Q3: 67 | R3: 2229 | S3: 458 | T3: 248 | U3: 67 | V3: 8957 | W3: 44 | X3: 4088 | Y3: 17 | Z3: 274-290 | AA3: 259 | AB3: 230.32 | AC3: - | AD3: 220.81 | AE3: 57 | AF3: - | AG3: 15431.44 | AH3: - | AI3: 217.3 | AJ3: - | AK3: 14559.1 | AL3: - | AM3: 2709 | AN3: 0.6491 | AO3: 0.4211 | AP3: 0.8777 | AQ3: 0.4902 | AR3: 0.9556 | AS3: 0.5645 | AT3: 2 | AU3: 0 | AV3: 1 | AW3: 0 | AX3: 0
A4: 11032744 | B4: 伯希和PELLIOT 岩壳 性能系列全防护单层硬壳防风防水专业登山服硬核外套耐磨时尚实用 冲锋衣 男女同款 | C4: PE1124101048 | D4: 伯希和/PELLIOT | E4: 服装-外套-冲锋衣 | F4: 一品多商 | G4: 品牌直发 | H4: 24142 | I4: =VLOOKUP(C4,[6]sheet1!$C:$X,6,0) -> 19889 | J4: =VLOOKUP(C4,[1]sheet1!$C:$I,6,0) -> 23017 | K4: =VLOOKUP(C4,[2]sheet1!$C:$H,6,0) -> 13499 | L4: =VLOOKUP(C4,[3]sheet1!$C:$H,6,0) -> 25984 | M4: =VLOOKUP(C4,[4]sheet1!$C:$I,6,0) -> 25861 | N4: =VLOOKUP(C4,[5]sheet1!$C:$J,6,0) -> 26185 | O4: =H4+I4+J4+K4+L4+M4+N4 -> 158577 | P4: 158577 | Q4: 43 | R4: 2030 | S4: 421 | T4: 235 | U4: 43 | V4: 8779 | W4: 15 | X4: 7166 | Y4: 13 | Z4: 621-690 | AA4: 499 | AB4: 529.42 | AC4: - | AD4: 561.44 | AE4: 40 | AF4: - | AG4: 22765.06 | AH4: - | AI4: 433.5 | AJ4: - | AK4: 18640.5 | AL4: - | AM4: 2583 | AN4: 0.775 | AO4: 0.4 | AP4: 0.8933 | AQ4: 0.6202 | AR4: 0.9149 | AS4: 0.6468 | AT4: 0 | AU4: 1 | AV4: 0 | AW4: 0 | AX4: 0
A5: 5812551 | B5: 伯希和PELLIOT 山壳 户外运动硬壳三层压胶单层防风防水登山服多巴胺宽松 冲锋衣 男女同款 | C5: 12340164 | D5: 伯希和/PELLIOT | E5: 服装-外套-冲锋衣 | F5: 一品多商 | G5: 品牌直发 | H5: 8474 | I5: =VLOOKUP(C5,[6]sheet1!$C:$X,6,0) -> 4206.71 | J5: =VLOOKUP(C5,[1]sheet1!$C:$I,6,0) -> 15668.61 | K5: =VLOOKUP(C5,[2]sheet1!$C:$H,6,0) -> 11223.71 | L5: =VLOOKUP(C5,[3]sheet1!$C:$H,6,0) -> 10531 | M5: =VLOOKUP(C5,[4]sheet1!$C:$I,6,0) -> 8342 | N5: =VLOOKUP(C5,[5]sheet1!$C:$J,6,0) -> 16839 | O5: =H5+I5+J5+K5+L5+M5+N5 -> 75285.03 | P5: 75285.03 | Q5: 16 | R5: 1366 | S5: 396 | T5: 86 | U5: 16 | V5: 5190 | W5: 10 | X5: 2252 | Y5: 6 | Z5: 608-699 | AA5: 494 | AB5: 518.13 | AC5: - | AD5: 529.62 | AE5: 16 | AF5: - | AG5: 8290.08 | AH5: - | AI5: 419.18 | AJ5: - | AK5: 6706.88 | AL5: - | AM5: 1721 | AN5: 0.6875 | AO5: 0.3125 | AP5: 0.8817 | AQ5: 0.4673 | AR5: 0.9419 | AS5: 0.5349 | AT5: 0 | AU5: 0 | AV5: 0 | AW5: 0 | AX5: 0
A6: 14644799 | B6: 伯希和PELLIOT 山野 经典2.0 徒步登山防水外套三合一可拆卸保暖抓绒内胆通勤时尚 冲锋衣 男款 | C6: 11340105-新加色 | D6: 伯希和/PELLIOT | E6: 服装-外套-冲锋衣 | F6: 一品多商 | G6: 品牌直发 | H6: 4577 | I6: =VLOOKUP(C6,[6]sheet1!$C:$X,6,0) -> 5619 | J6: =VLOOKUP(C6,[1]sheet1!$C:$I,6,0) -> 8757 | K6: =VLOOKUP(C6,[2]sheet1!$C:$H,6,0) -> 4451 | L6: =VLOOKUP(C6,[3]sheet1!$C:$H,6,0) -> 478 | M6: =VLOOKUP(C6,[4]sheet1!$C:$I,6,0) -> 3017 | N6: =VLOOKUP(C6,[5]sheet1!$C:$J,6,0) -> 3366 | O6: =H6+I6+J6+K6+L6+M6+N6 -> 30265 | P6: 30265 | Q6: 11 | R6: 1255 | S6: 341 | T6: 65 | U6: 11 | V6: 1782 | W6: 4 | X6: 1724 | Y6: 4 | Z6: 440-499 | AA6: 401 | AB6: 372.31 | AC6: - | AD6: 416.09 | AE6: 10 | AF6: - | AG6: 4095.41 | AH6: - | AI6: 362.52 | AJ6: - | AK6: 3987.72 | AL6: - | AM6: 1556 | AN6: 0.7 | AO6: 0.6 | AP6: 0.8727 | AQ6: 0.5838 | AR6: 0.9692 | AS6: 0.6615 | AT6: 0 | AU6: 0 | AV6: 0 | AW6: 0 | AX6: 0
A7: 20699631 | B7: 伯希和PELLIOT 小森林UPF50+舒适运动户外轻薄透气凉感纯色宽松防紫外线轻量连帽外套穿搭 防水超轻防晒服 男女同款 | C7: 12421220-新加色 | D7: 伯希和/PELLIOT | E7: 服装-外套-防晒服 | F7: 一品多商 | G7: 品牌直发 | H7: 2473 | I7: =VLOOKUP(C7,[6]sheet1!$C:$X,6,0) -> 4057 | J7: =VLOOKUP(C7,[1]sheet1!$C:$I,6,0) -> 3356 | K7: =VLOOKUP(C7,[2]sheet1!$C:$H,6,0) -> 474 | L7: =VLOOKUP(C7,[3]sheet1!$C:$H,6,0) -> 1977 | M7: =VLOOKUP(C7,[4]sheet1!$C:$I,6,0) -> 1931 | N7: =VLOOKUP(C7,[5]sheet1!$C:$J,6,0) -> 2457 | O7: =H7+I7+J7+K7+L7+M7+N7 -> 16725 | P7: 16725 | Q7: 10 | R7: 1121 | S7: 362 | T7: 54 | U7: 10 | V7: 792 | W7: 3 | X7: 789 | Y7: 3 | Z7: 274-299 | AA7: 257 | AB7: 230.32 | AC7: - | AD7: 247.3 | AE7: 9 | AF7: - | AG7: 2303.2 | AH7: - | AI7: 215.57 | AJ7: - | AK7: 2155.7 | AL7: - | AM7: 1268 | AN7: 0.8889 | AO7: 0.5556 | AP7: 0.9159 | AQ7: 0.5603 | AR7: 0.9444 | AS7: 0.5741 | AT7: 0 | AU7: 0 | AV7: 0 | AW7: 0 | AX7: 0
A8: 6588514 | B8: 伯希和PELLIOT 山壳 全天候硬壳户外工装裤防风防水登山徒步运动 透气耐磨时尚耐用多巴胺冲锋裤 男款 | C8: 11410201 | D8: 伯希和/PELLIOT | E8: 服装-长裤-冲锋裤 | F8: 一品多商 | G8: 品牌直发 | H8: 2677 | I8: =VLOOKUP(C8,[6]sheet1!$C:$X,6,0) -> 6466 | J8: =VLOOKUP(C8,[1]sheet1!$C:$I,6,0) -> 3530 | K8: =VLOOKUP(C8,[2]sheet1!$C:$H,6,0) -> 3361 | L8: =VLOOKUP(C8,[3]sheet1!$C:$H,6,0) -> 6314.9 | M8: =VLOOKUP(C8,[4]sheet1!$C:$I,6,0) -> 5164 | N8: =VLOOKUP(C8,[5]sheet1!$C:$J,6,0) -> 5566 | O8: =H8+I8+J8+K8+L8+M8+N8 -> 33078.9 | P8: 33078.9 | Q8: 8 | R8: 1406 | S8: 255 | T8: 103 | U8: 8 | V8: 2027 | W8: 5 | X8: 408 | Y8: 2 | Z8: 437-482 | AA8: 389 | AB8: 371.71 | AC8: - | AD8: 334.62 | AE8: 7 | AF8: - | AG8: 2973.68 | AH8: - | AI8: 345.6 | AJ8: - | AK8: 2764.8 | AL8: - | AM8: 1673 | AN8: 0.7143 | AO8: 0.4286 | AP8: 0.8344 | AQ8: 0.5565 | AR8: 0.8738 | AS8: 0.6214 | AT8: 0 | AU8: 0 | AV8: 0 | AW8: 0 | AX8: 0
A9: 5201433 | B9: 伯希和PELLIOT 经典2.0 山野 户外徒步登山运动防风防水透气保暖抓绒内胆可拆卸通勤三合一 冲锋衣 男款 | C9: 11340105 | D9: 伯希和/PELLIOT | E9: 服装-外套-冲锋衣 | F9: 一品多商 | G9: 品牌直发 | H9: 3445.66 | I9: =VLOOKUP(C9,[6]sheet1!$C:$X,6,0) -> 7155 | J9: =VLOOKUP(C9,[1]sheet1!$C:$I,6,0) -> 2572 | K9: =VLOOKUP(C9,[2]sheet1!$C:$H,6,0) -> 4603 | L9: =VLOOKUP(C9,[3]sheet1!$C:$H,6,0) -> 0 | M9: =VLOOKUP(C9,[4]sheet1!$C:$I,6,0) -> 1374 | N9: =VLOOKUP(C9,[5]sheet1!$C:$J,6,0) -> 3155 | O9: =H9+I9+J9+K9+L9+M9+N9 -> 22304.66 | P9: 22304.66 | Q9: 8 | R9: 1380 | S9: 278 | T9: 83 | U9: 8 | V9: 937 | W9: 2 | X9: 1793 | Y9: 4 | Z9: 437-489 | AA9: 389 | AB9: 369.71 | AC9: - | AD9: 430.71 | AE9: 8 | AF9: - | AG9: 2957.68 | AH9: - | AI9: 335.82 | AJ9: - | AK9: 2686.56 | AL9: - | AM9: 1728 | AN9: 0.75 | AO9: 0.25 | AP9: 0.877 | AQ9: 0.634 | AR9: 0.9759 | AS9: 0.6867 | AT9: 0 | AU9: 0 | AV9: 0 | AW9: 0 | AX9: 0
A10: 19612287 | B10: 伯希和PELLIOT HT-远见 专业户外运动Vibram登山鞋网面透气全地形轻量 低帮 徒步鞋 男款 | C10: 115119035 | D10: 伯希和/PELLIOT | E10: 鞋-运动鞋-登山鞋/徒步鞋 | F10: 一品多商 | G10: 品牌直发 | H10: 3004 | I10: =VLOOKUP(C10,[6]sheet1!$C:$X,6,0) -> 1854.45 | J10: =VLOOKUP(C10,[1]sheet1!$C:$I,6,0) -> 2931 | K10: =VLOOKUP(C10,[2]sheet1!$C:$H,6,0) -> 2197.1 | L10: =VLOOKUP(C10,[3]sheet1!$C:$H,6,0) -> 4488 | M10: =VLOOKUP(C10,[4]sheet1!$C:$I,6,0) -> 3025 | N10: =VLOOKUP(C10,[5]sheet1!$C:$J,6,0) -> 2603 | O10: =H10+I10+J10+K10+L10+M10+N10 -> 20102.55 | P10: 20102.55 | Q10: 8 | R10: 1226 | S10: 312 | T10: 60 | U10: 8 | V10: 1225 | W10: 4 | X10: 408 | Y10: 2 | Z10: 499-499 | AA10: 399 | AB10: 424.03 | AC10: - | AD10: 375.5 | AE10: 8 | AF10: - | AG10: 3392.24 | AH10: - | AI10: 337.23 | AJ10: - | AK10: 2697.84 | AL10: - | AM10: 1470 | AN10: 0.75 | AO10: 0.625 | AP10: 0.8254 | AQ10: 0.3267 | AR10: 0.8333 | AS10: 0.45 | AT10: 0 | AU10: 0 | AV10: 0 | AW10: 0 | AX10: 0
A11: 19113828 | B11: 伯希和PELLIOT ct-驰风 户外运动通勤包裹性增高平衡缓震系带徒步轻量TPU透气Blast中底防撞击网面 越野跑鞋 鞋子男 | C11: 115119025 | D11: 伯希和/PELLIOT | E11: 鞋-运动鞋-越野跑鞋 | F11: 一品多商 | G11: 品牌直发 | H11: 2303.27 | I11: =VLOOKUP(C11,[6]sheet1!$C:$X,6,0) -> 3097.2 | J11: =VLOOKUP(C11,[1]sheet1!$C:$I,6,0) -> 2071 | K11: =VLOOKUP(C11,[2]sheet1!$C:$H,6,0) -> 2045 | L11: =VLOOKUP(C11,[3]sheet1!$C:$H,6,0) -> 2255 | M11: =VLOOKUP(C11,[4]sheet1!$C:$I,6,0) -> 1691 | N11: =VLOOKUP(C11,[5]sheet1!$C:$J,6,0) -> 2881 | O11: =H11+I11+J11+K11+L11+M11+N11 -> 16343.47 | P11: 16343.47 | Q11: 8 | R11: 1232 | S11: 310 | T11: 42 | U11: 8 | V11: 626 | W11: 2 | X11: 626 | Y11: 2 | Z11: 354-399 | AA11: 322 | AB11: 297.37 | AC11: - | AD11: 287.91 | AE11: 8 | AF11: - | AG11: 2378.96 | AH11: - | AI11: 272.82 | AJ11: - | AK11: 2182.56 | AL11: - | AM11: 1423 | AN11: 0.5 | AO11: 0.125 | AP11: 0.8466 | AQ11: 0.3907 | AR11: 0.8095 | AS11: 0.3571 | AT11: 1 | AU11: 0 | AV11: 1 | AW11: 0 | AX11: 0
A12: 19281657 | B12: 伯希和PELLIOT 小光盾专业版UPF50+防紫外线外套皮肤衣运动户外舒适百搭轻薄透气宽松 速干防晒服 男女同款 | C12: 105212020 | D12: 伯希和/PELLIOT | E12: 服装-外套-防晒服 | F12: 一品多商 | G12: 品牌直发 | H12: 1790 | I12: =VLOOKUP(C12,[6]sheet1!$C:$X,6,0) -> 1278 | J12: =VLOOKUP(C12,[1]sheet1!$C:$I,6,0) -> 1070 | K12: =VLOOKUP(C12,[2]sheet1!$C:$H,6,0) -> 1043 | L12: =VLOOKUP(C12,[3]sheet1!$C:$H,6,0) -> 506 | M12: =VLOOKUP(C12,[4]sheet1!$C:$I,6,0) -> 0 | N12: =VLOOKUP(C12,[5]sheet1!$C:$J,6,0) -> 736 | O12: =H12+I12+J12+K12+L12+M12+N12 -> 6423 | P12: 6423 | Q12: 7 | R12: 1386 | S12: 258 | T12: 61 | U12: 7 | V12: 0 | W12: 0 | X12: 296 | Y12: 2 | Z12: 235-235 | AA12: 222 | AB12: 196.47 | AC12: - | AD12: 255.71 | AE12: 7 | AF12: - | AG12: 1375.29 | AH12: - | AI12: 185.19 | AJ12: - | AK12: 1296.33 | AL12: - | AM12: 1640 | AN12: 0.7143 | AO12: 0.4286 | AP12: 0.8901 | AQ12: 0.4235 | AR12: 0.8525 | AS12: 0.4426 | AT12: 1 | AU12: 0 | AV12: 1 | AW12: 0 | AX12: 0
A13: 9755754 | B13: 伯希和PELLIOT 小光盾 冰丝专upf50+皮肤衣业 透气防水防紫外线防晒服 女款 | C13: 12421252 | D13: 伯希和/PELLIOT | E13: 女装-外套-防晒服 | F13: 一品多商 | G13: 品牌直发 | H13: 605 | I13: =VLOOKUP(C13,[6]sheet1!$C:$X,6,0) -> 842 | J13: =VLOOKUP(C13,[1]sheet1!$C:$I,6,0) -> 1027 | K13: =VLOOKUP(C13,[2]sheet1!$C:$H,6,0) -> 955 | L13: =VLOOKUP(C13,[3]sheet1!$C:$H,6,0) -> 623 | M13: =VLOOKUP(C13,[4]sheet1!$C:$I,6,0) -> 945 | N13: =VLOOKUP(C13,[5]sheet1!$C:$J,6,0) -> 285 | O13: =H13+I13+J13+K13+L13+M13+N13 -> 5282 | P13: 5282 | Q13: 6 | R13: 546 | S13: 554 | T13: 2 | U13: 6 | V13: 238 | W13: 2 | X13: 11 | Y13: 1 | Z13: 119-119 | AA13: 93 | AB13: 95.3 | AC13: - | AD13: 100.83 | AE13: 5 | AF13: - | AG13: 571.8 | AH13: - | AI13: 72.73 | AJ13: - | AK13: 436.38 | AL13: - | AM13: 641 | AN13: 0.4 | AO13: 0.2 | AP13: 0.8 | AQ13: 0.4364 | AR13: 1 | AS13: 0.5 | AT13: 0 | AU13: 0 | AV13: 0 | AW13: 0 | AX13: 0
A14: 4460998 | B14: 伯希和PELLIOT 经典1.0 户外薄款夏季登山裤防风超轻透气凉感耐脏耐洗抗皱耐磨立体剪裁显瘦快干裤弹力徒步裤运动休闲裤 男款 | C14: 115214025 | D14: 伯希和/PELLIOT | E14: 服装-户外运动服-速干裤 | F14: 一品多商 | G14: 品牌直发 | H14: 1377 | I14: =VLOOKUP(C14,[6]sheet1!$C:$X,6,0) -> 961 | J14: =VLOOKUP(C14,[1]sheet1!$C:$I,6,0) -> 720 | K14: =VLOOKUP(C14,[2]sheet1!$C:$H,6,0) -> 0 | L14: =VLOOKUP(C14,[3]sheet1!$C:$H,6,0) -> 234 | M14: =VLOOKUP(C14,[4]sheet1!$C:$I,6,0) -> 484 | N14: =VLOOKUP(C14,[5]sheet1!$C:$J,6,0) -> 484 | O14: =H14+I14+J14+K14+L14+M14+N14 -> 4260 | P14: 4260 | Q14: 6 | R14: 646 | S14: 514 | T14: 11 | U14: 6 | V14: 0 | W14: 0 | X14: 470 | Y14: 2 | Z14: 287-299 | AA14: 259 | AB14: 240.31 | AC14: - | AD14: 229.5 | AE14: 6 | AF14: - | AG14: 1441.86 | AH14: - | AI14: 216 | AJ14: - | AK14: 1296 | AL14: - | AM14: 812 | AN14: 0.3333 | AO14: 0.3333 | AP14: 0.6753 | AQ14: 0.2825 | AR14: 1 | AS14: 0 | AT14: 0 | AU14: 0 | AV14: 0 | AW14: 0 | AX14: 0
A15: 3945985 | B15: 伯希和PELLIOT 经典1.0系列 户外防晒舒适运动薄款长裤吸湿排汗轻盈透气不闷汗徒步凉感登山速干裤 男款 | C15: 115214024 | D15: 伯希和/PELLIOT | E15: 服装-户外运动服-速干裤 | F15: 一品多商 | G15: 品牌直发 | H15: 1019 | I15: =VLOOKUP(C15,[6]sheet1!$C:$X,6,0) -> 190 | J15: =VLOOKUP(C15,[1]sheet1!$C:$I,6,0) -> 2264 | K15: =VLOOKUP(C15,[2]sheet1!$C:$H,6,0) -> 931 | L15: =VLOOKUP(C15,[3]sheet1!$C:$H,6,0) -> 3291.64 | M15: =VLOOKUP(C15,[4]sheet1!$C:$I,6,0) -> 2071 | N15: =VLOOKUP(C15,[5]sheet1!$C:$J,6,0) -> 1964 | O15: =H15+I15+J15+K15+L15+M15+N15 -> 11730.64 | P15: 11730.64 | Q15: 6 | R15: 1213 | S15: 273 | T15: 42 | U15: 6 | V15: 158 | W15: 1 | X15: 0 | Y15: 0 | Z15: 196-198 | AA15: 174 | AB15: 161.32 | AC15: - | AD15: 169.83 | AE15: 6 | AF15: - | AG15: 967.92 | AH15: - | AI15: 142.22 | AJ15: - | AK15: 853.32 | AL15: - | AM15: 1408 | AN15: 0.8333 | AO15: 0.5 | AP15: 0.7728 | AQ15: 0.3257 | AR15: 0.7857 | AS15: 0.3571 | AT15: 0 | AU15: 0 | AV15: 0 | AW15: 0 | AX15: 0
A16: 19092701 | B16: 伯希和PELLIOT 岩壳新加色 宽松户外硬壳专业运动跑步百搭登山服外套 徒步滑雪 透气耐磨冲锋衣 男女同款 | C16: 124101048-新加色 | D16: 伯希和/PELLIOT | E16: 服装-外套-冲锋衣 | F16: 一品多商 | G16: 品牌直发 | H16: 3768 | I16: =VLOOKUP(C16,[6]sheet1!$C:$X,6,0) -> 0 | J16: =VLOOKUP(C16,[1]sheet1!$C:$I,6,0) -> 0 | K16: =VLOOKUP(C16,[2]sheet1!$C:$H,6,0) -> 0 | L16: =VLOOKUP(C16,[3]sheet1!$C:$H,6,0) -> 627 | M16: =VLOOKUP(C16,[4]sheet1!$C:$I,6,0) -> 1274 | N16: =VLOOKUP(C16,[5]sheet1!$C:$J,6,0) -> 0 | O16: =H16+I16+J16+K16+L16+M16+N16 -> 5669 | P16: 5669 | Q16: 6 | R16: 2074 | S16: 160 | T16: 218 | U16: 6 | V16: 0 | W16: 0 | X16: 1310 | Y16: 2 | Z16: 640-690 | AA16: 546 | AB16: 545.91 | AC16: - | AD16: 628 | AE16: 6 | AF16: - | AG16: 3275.46 | AH16: - | AI16: 469.78 | AJ16: - | AK16: 2818.68 | AL16: - | AM16: 2259 | AN16: 1 | AO16: 0.8333 | AP16: 0.9346 | AQ16: 0.5768 | AR16: 0.9495 | AS16: 0.6284 | AT16: 0 | AU16: 0 | AV16: 0 | AW16: 0 | AX16: 0
A17: 8590436 | B17: 伯希和PELLIOT 户外运动速干裤高弹透气徒步裤子休闲束脚跑步舒适百搭通勤长裤登山裤 男女同款 | C17: 11421425 | D17: 伯希和/PELLIOT | E17: 服装-长裤-针织运动裤 | F17: 一品多商 | G17: 品牌直发 | H17: 735 | I17: =VLOOKUP(C17,[6]sheet1!$C:$X,6,0) -> 873 | J17: =VLOOKUP(C17,[1]sheet1!$C:$I,6,0) -> 445 | K17: =VLOOKUP(C17,[2]sheet1!$C:$H,6,0) -> 580 | L17: =VLOOKUP(C17,[3]sheet1!$C:$H,6,0) -> 746 | M17: =VLOOKUP(C17,[4]sheet1!$C:$I,6,0) -> 580 | N17: =VLOOKUP(C17,[5]sheet1!$C:$J,6,0) -> 415 | O17: =H17+I17+J17+K17+L17+M17+N17 -> 4374 | P17: 4374 | Q17: 5 | R17: 427 | S17: 633 | T17: 7 | U17: 5 | V17: 160 | W17: 1 | X17: 160 | Y17: 1 | Z17: 135-135 | AA17: 108 | AB17: 110.07 | AC17: - | AD17: 147 | AE17: 4 | AF17: - | AG17: 550.35 | AH17: - | AI17: 86.63 | AJ17: - | AK17: 433.15 | AL17: - | AM17: 533 | AN17: 0.5 | AO17: 0 | AP17: 0.637 | AQ17: 0.1259 | AR17: 0.8571 | AS17: 0 | AT17: 0 | AU17: 0 | AV17: 0 | AW17: 0 | AX17: 0
A18: 4089091 | B18: 伯希和PELLIOT 经典1.0 小光盾UPF50+户外轻薄透气休闲凉感连帽防紫外线皮肤衣防晒服 女款 | C18: 12321218 | D18: 伯希和/PELLIOT | E18: 女装-外套-防晒服 | F18: 一品多商 | G18: 品牌直发 | H18: 426 | I18: =VLOOKUP(C18,[6]sheet1!$C:$X,6,0) -> 1287 | J18: =VLOOKUP(C18,[1]sheet1!$C:$I,6,0) -> 819 | K18: =VLOOKUP(C18,[2]sheet1!$C:$H,6,0) -> 424 | L18: =VLOOKUP(C18,[3]sheet1!$C:$H,6,0) -> 343 | M18: =VLOOKUP(C18,[4]sheet1!$C:$I,6,0) -> 166 | N18: =VLOOKUP(C18,[5]sheet1!$C:$J,6,0) -> 490.95 | O18: =H18+I18+J18+K18+L18+M18+N18 -> 3955.95 | P18: 3955.95 | Q18: 5 | R18: 1379 | S18: 221 | T18: 63 | U18: 5 | V18: 91 | W18: 1 | X18: 0 | Y18: 0 | Z18: - | AA18: 95 | AB18: - | AC18: - | AD18: 85.2 | AE18: 5 | AF18: - | AG18: - | AH18: - | AI18: 74.47 | AJ18: - | AK18: 372.35 | AL18: - | AM18: 1624 | AN18: 0.8 | AO18: 0.6 | AP18: 0.8677 | AQ18: 0.569 | AR18: 0.9365 | AS18: 0.6349 | AT18: 0 | AU18: 0 | AV18: 0 | AW18: 0 | AX18: 0
A19: 5201435 | B19: 伯希和PELLIOT 山野 登山徒步抓绒内胆可拆卸三合一通勤穿搭 防水防风透气防泼水耐磨保暖冲锋衣 女款 | C19: 12340106 | D19: 伯希和/PELLIOT | E19: 女装-外套-冲锋衣 | F19: 一品多商 | G19: 品牌直发 | H19: 1648 | I19: =VLOOKUP(C19,[6]sheet1!$C:$X,6,0) -> 5670 | J19: =VLOOKUP(C19,[1]sheet1!$C:$I,6,0) -> 8665 | K19: =VLOOKUP(C19,[2]sheet1!$C:$H,6,0) -> 8874 | L19: =VLOOKUP(C19,[3]sheet1!$C:$H,6,0) -> 7798 | M19: =VLOOKUP(C19,[4]sheet1!$C:$I,6,0) -> 4102 | N19: =VLOOKUP(C19,[5]sheet1!$C:$J,6,0) -> 4896 | O19: =H19+I19+J19+K19+L19+M19+N19 -> 41653 | P19: 41653 | Q19: 4 | R19: 1593 | S19: 169 | T19: 137 | U19: 4 | V19: 2602 | W19: 6 | X19: 1264 | Y19: 3 | Z19: 404-428 | AA19: 365 | AB19: 339.28 | AC19: - | AD19: 412 | AE19: 4 | AF19: - | AG19: 1357.12 | AH19: - | AI19: 305.43 | AJ19: - | AK19: 1221.72 | AL19: - | AM19: 1908 | AN19: 0.75 | AO19: 0.75 | AP19: 0.9147 | AQ19: 0.6155 | AR19: 0.9343 | AS19: 0.7007 | AT19: 0 | AU19: 0 | AV19: 0 | AW19: 0 | AX19: 0
A20: 20415380 | B20: 伯希和PELLIOT 轻风2.0 UPF50+轻量轻薄凉感专业户外运动跑步百搭休闲 透气防紫外线超轻防晒服 男款 | C20: 115212003 | D20: 伯希和/PELLIOT | E20: 服装-外套-防晒服 | F20: 一品多商 | G20: 品牌直发 | H20: 606 | I20: =VLOOKUP(C20,[6]sheet1!$C:$X,6,0) -> 1002 | J20: =VLOOKUP(C20,[1]sheet1!$C:$I,6,0) -> 404 | K20: =VLOOKUP(C20,[2]sheet1!$C:$H,6,0) -> 208 | L20: =VLOOKUP(C20,[3]sheet1!$C:$H,6,0) -> 606 | M20: =VLOOKUP(C20,[4]sheet1!$C:$I,6,0) -> 606 | N20: =VLOOKUP(C20,[5]sheet1!$C:$J,6,0) -> 404 | O20: =H20+I20+J20+K20+L20+M20+N20 -> 3836 | P20: 3836 | Q20: 3 | R20: 885 | S20: 218 | T20: 21 | U20: 3 | V20: 0 | W20: 0 | X20: 0 | Y20: 0 | Z20: 246-269 | AA20: 246 | AB20: 206.02 | AC20: - | AD20: 202 | AE20: 2 | AF20: - | AG20: 618.06 | AH20: - | AI20: - | AJ20: - | AK20: - | AL20: - | AM20: 1060 | AN20: 0.5 | AO20: 0 | AP20: 0.8048 | AQ20: 0.4542 | AR20: 0.9048 | AS20: 0.5238 | AT20: 0 | AU20: 0 | AV20: 0 | AW20: 0 | AX20: 0
A21: 9553216 | B21: 伯希和PELLIOT 山壳 全天候专业户外运动跑步时尚潮流硬壳登山服外套宽松 防水防风透气耐磨保暖冲锋衣 男女同款 | C21: 112340164-271037 | D21: 伯希和/PELLIOT | E21: 服装-外套-冲锋衣 | F21: 一品多商 | G21: 品牌直发 | H21: 1264 | I21: =VLOOKUP(C21,[6]sheet1!$C:$X,6,0) -> 0 | J21: =VLOOKUP(C21,[1]sheet1!$C:$I,6,0) -> 0 | K21: =VLOOKUP(C21,[2]sheet1!$C:$H,6,0) -> 0 | L21: =VLOOKUP(C21,[3]sheet1!$C:$H,6,0) -> 643 | M21: =VLOOKUP(C21,[4]sheet1!$C:$I,6,0) -> 1285 | N21: =VLOOKUP(C21,[5]sheet1!$C:$J,6,0) -> 646 | O21: =H21+I21+J21+K21+L21+M21+N21 -> 3838 | P21: 3838 | Q21: 2 | R21: 512 | S21: 265 | T21: 14 | U21: 2 | V21: 0 | W21: 0 | X21: 654 | Y21: 1 | Z21: 629-699 | AA21: 629 | AB21: 536.36 | AC21: - | AD21: 632 | AE21: 1 | AF21: - | AG21: 1072.72 | AH21: - | AI21: - | AJ21: - | AK21: - | AL21: - | AM21: 608 | AN21: 1 | AO21: 1 | AP21: 0.8866 | AQ21: 0.3608 | AR21: 0.8571 | AS21: 0.7143 | AT21: 0 | AU21: 0 | AV21: 0 | AW21: 0 | AX21: 0
A22: 9073622 | B22: 伯希和PELLIOT 户外夏季凉感薄款登山徒步速干衣抑菌轻弹休闲百搭 运动柔软亲肤正肩打底短袖Polo衫 男女同款 | C22: 11421533 | D22: 伯希和/PELLIOT | E22: 服装-上衣-Polo衫 | F22: 一品多商 | G22: 品牌直发 | H22: 344 | I22: =VLOOKUP(C22,[6]sheet1!$C:$X,6,0) -> 1589 | J22: =VLOOKUP(C22,[1]sheet1!$C:$I,6,0) -> 1672 | K22: =VLOOKUP(C22,[2]sheet1!$C:$H,6,0) -> 1004 | L22: =VLOOKUP(C22,[3]sheet1!$C:$H,6,0) -> 1764 | M22: =VLOOKUP(C22,[4]sheet1!$C:$I,6,0) -> 1934 | N22: =VLOOKUP(C22,[5]sheet1!$C:$J,6,0) -> 1215 | O22: =H22+I22+J22+K22+L22+M22+N22 -> 9522 | P22: 9522 | Q22: 2 | R22: 2362 | S22: 82 | T22: 182 | U22: 2 | V22: 642 | W22: 3 | X22: 163 | Y22: 1 | Z22: 232-249 | AA22: 201 | AB22: 192.97 | AC22: - | AD22: 172 | AE22: 2 | AF22: - | AG22: 385.94 | AH22: - | AI22: 166.06 | AJ22: - | AK22: 332.12 | AL22: - | AM22: 2681 | AN22: 1 | AO22: 0.5 | AP22: 0.8603 | AQ22: 0.4306 | AR22: 0.8571 | AS22: 0.4505 | AT22: 0 | AU22: 0 | AV22: 0 | AW22: 0 | AX22: 0
A23: 8925860 | B23: 伯希和PELLIOT 户外夏季速干圆领Polo衫款休闲短袖抑菌排汗登山徒步跑步健身运动T恤 男女同款 | C23: 11421509 | D23: 伯希和/PELLIOT | E23: 服装-上衣-T恤 | F23: 一品多商 | G23: 品牌直发 | H23: 258 | I23: =VLOOKUP(C23,[6]sheet1!$C:$X,6,0) -> 0 | J23: =VLOOKUP(C23,[1]sheet1!$C:$I,6,0) -> 0 | K23: =VLOOKUP(C23,[2]sheet1!$C:$H,6,0) -> 0 | L23: =VLOOKUP(C23,[3]sheet1!$C:$H,6,0) -> 0 | M23: =VLOOKUP(C23,[4]sheet1!$C:$I,6,0) -> 373 | N23: =VLOOKUP(C23,[5]sheet1!$C:$J,6,0) -> 108 | O23: =H23+I23+J23+K23+L23+M23+N23 -> 739 | P23: 739 | Q23: 2 | R23: 1187 | S23: 160 | T23: 34 | U23: 2 | V23: 141 | W23: 1 | X23: 0 | Y23: 0 | Z23: 125-139 | AA23: 114 | AB23: 101.29 | AC23: - | AD23: 129 | AE23: 2 | AF23: - | AG23: 202.58 | AH23: - | AI23: 91.74 | AJ23: - | AK23: 183.48 | AL23: - | AM23: 1355 | AN23: 0.5 | AO23: 0.5 | AP23: 0.7867 | AQ23: 0.2555 | AR23: 0.6471 | AS23: 0.2941 | AT23: 0 | AU23: 0 | AV23: 0 | AW23: 0 | AX23: 0
A24: 6273814 | B24: 伯希和PELLIOT 经典2.0 排骨户外超轻东丽面料800蓬95%轻奢鹅绒防风轻量保暖立领百搭舒适防钻绒短款羽绒服 女款 | C24: 12340822 | D24: 伯希和/PELLIOT | E24: 女装-外套-羽绒服 | F24: 一品多商 | G24: 品牌直发 | H24: 1177 | I24: =VLOOKUP(C24,[6]sheet1!$C:$X,6,0) -> 591 | J24: =VLOOKUP(C24,[1]sheet1!$C:$I,6,0) -> 0 | K24: =VLOOKUP(C24,[2]sheet1!$C:$H,6,0) -> 0 | L24: =VLOOKUP(C24,[3]sheet1!$C:$H,6,0) -> 0 | M24: =VLOOKUP(C24,[4]sheet1!$C:$I,6,0) -> 0 | N24: =VLOOKUP(C24,[5]sheet1!$C:$J,6,0) -> 0 | O24: =H24+I24+J24+K24+L24+M24+N24 -> 1768 | P24: 1768 | Q24: 2 | R24: 961 | S24: 142 | T24: 34 | U24: 2 | V24: 0 | W24: 0 | X24: 0 | Y24: 0 | Z24: 650-650 | AA24: 565 | AB24: 552.71 | AC24: - | AD24: 588.5 | AE24: 1 | AF24: - | AG24: 1105.42 | AH24: - | AI24: 478.93 | AJ24: - | AK24: 957.86 | AL24: - | AM24: 1077 | AN24: 0 | AO24: 0 | AP24: 0.9488 | AQ24: 0.6266 | AR24: 0.8824 | AS24: 0.6471 | AT24: 0 | AU24: 0 | AV24: 0 | AW24: 0 | AX24: 0
A25: 5938599 | B25: 伯希和PELLIOT 北极星 40D eVent面料专业户外全天候三层硬壳运动军工级单层 徒步 防水防风冲锋衣 男女同款 | C25: 114301085 | D25: 伯希和/PELLIOT | E25: 服装-外套-冲锋衣 | F25: 一品多商 | G25: 品牌直发 | H25: 3542 | I25: =VLOOKUP(C25,[6]sheet1!$C:$X,6,0) -> 0 | J25: =VLOOKUP(C25,[1]sheet1!$C:$I,6,0) -> 0 | K25: =VLOOKUP(C25,[2]sheet1!$C:$H,6,0) -> 0 | L25: =VLOOKUP(C25,[3]sheet1!$C:$H,6,0) -> 0 | M25: =VLOOKUP(C25,[4]sheet1!$C:$I,6,0) -> 1575 | N25: =VLOOKUP(C25,[5]sheet1!$C:$J,6,0) -> 0 | O25: =H25+I25+J25+K25+L25+M25+N25 -> 5117 | P25: 5117 | Q25: 2 | R25: 467 | S25: 290 | T25: 9 | U25: 2 | V25: 0 | W25: 0 | X25: 0 | Y25: 0 | Z25: 1681-1700 | AA25: 1057 | AB25: 1449.5 | AC25: - | AD25: 1771 | AE25: 1 | AF25: - | AG25: 2899 | AH25: - | AI25: 907.87 | AJ25: - | AK25: 1815.74 | AL25: - | AM25: 582 | AN25: 1 | AO25: 0 | AP25: 0.8261 | AQ25: 0.4783 | AR25: 0.6667 | AS25: 0.6667 | AT25: 0 | AU25: 0 | AV25: 0 | AW25: 0 | AX25: 0
A26: 19209381 | B26: 伯希和PELLIOT 山野 3.0 徒步接缝全压胶三合一可拆卸内胆 防水防风透气耐磨保暖冲锋衣 男款 | C26: 115301054 | D26: 伯希和/PELLIOT | E26: 服装-外套-冲锋衣 | F26: 一品多商 | G26: 品牌直发 | H26: 1094 | I26: =VLOOKUP(C26,[6]sheet1!$C:$X,6,0) -> 0 | J26: =VLOOKUP(C26,[1]sheet1!$C:$I,6,0) -> 0 | K26: =VLOOKUP(C26,[2]sheet1!$C:$H,6,0) -> 0 | L26: =VLOOKUP(C26,[3]sheet1!$C:$H,6,0) -> 0 | M26: =VLOOKUP(C26,[4]sheet1!$C:$I,6,0) -> 547 | N26: =VLOOKUP(C26,[5]sheet1!$C:$J,6,0) -> 0 | O26: =H26+I26+J26+K26+L26+M26+N26 -> 1641 | P26: 1641 | Q26: 2 | R26: 559 | S26: 241 | T26: 12 | U26: 2 | V26: 0 | W26: 0 | X26: 0 | Y26: 0 | Z26: 542-589 | AA26: 480 | AB26: 460.85 | AC26: - | AD26: 547 | AE26: 1 | AF26: - | AG26: 921.7 | AH26: - | AI26: 421.43 | AJ26: - | AK26: 842.86 | AL26: - | AM26: 654 | AN26: 1 | AO26: 0 | AP26: 0.8571 | AQ26: 0.4459 | AR26: 1 | AS26: 0.5 | AT26: 0 | AU26: 0 | AV26: 0 | AW26: 0 | AX26: 0
A27: 15766423 | B27: 伯希和PELLIOT 山野 经典2.0 650蓬鹅绒内胆可拆卸登山户外三合一防水通勤保暖防风 冲锋衣 男款 | C27: 114401041 | D27: 伯希和/PELLIOT | E27: 服装-外套-冲锋衣 | F27: 一品多商 | G27: 品牌直发 | H27: 1851 | I27: =VLOOKUP(C27,[6]sheet1!$C:$X,6,0) -> 0 | J27: =VLOOKUP(C27,[1]sheet1!$C:$I,6,0) -> 936 | K27: =VLOOKUP(C27,[2]sheet1!$C:$H,6,0) -> 0 | L27: =VLOOKUP(C27,[3]sheet1!$C:$H,6,0) -> 0 | M27: =VLOOKUP(C27,[4]sheet1!$C:$I,6,0) -> 913 | N27: =VLOOKUP(C27,[5]sheet1!$C:$J,6,0) -> 0 | O27: =H27+I27+J27+K27+L27+M27+N27 -> 3700 | P27: 3700 | Q27: 2 | R27: 589 | S27: 325 | T27: 10 | U27: 2 | V27: 0 | W27: 0 | X27: 0 | Y27: 0 | Z27: 878-990 | AA27: 789 | AB27: 752.49 | AC27: - | AD27: 925.5 | AE27: 2 | AF27: - | AG27: 1504.98 | AH27: - | AI27: 675.24 | AJ27: - | AK27: 1350.48 | AL27: - | AM27: 701 | AN27: 0.5 | AO27: 0.5 | AP27: 0.8359 | AQ27: 0.4062 | AR27: 0.8 | AS27: 0.5 | AT27: 0 | AU27: 0 | AV27: 0 | AW27: 0 | AX27: 0
A28: 11848257 | B28: 伯希和PELLIOT 原石 户外三合一防风防水防雨透气保暖舒适耐磨时尚抓绒可拆连帽内胆 冲锋衣 男款 | C28: 114301029 | D28: 伯希和/PELLIOT | E28: 服装-外套-冲锋衣 | F28: 一品多商 | G28: 品牌直发 | H28: 876.74 | I28: =VLOOKUP(C28,[6]sheet1!$C:$X,6,0) -> 1554.74 | J28: =VLOOKUP(C28,[1]sheet1!$C:$I,6,0) -> 0 | K28: =VLOOKUP(C28,[2]sheet1!$C:$H,6,0) -> 0 | L28: =VLOOKUP(C28,[3]sheet1!$C:$H,6,0) -> 1027 | M28: =VLOOKUP(C28,[4]sheet1!$C:$I,6,0) -> 2523 | N28: =VLOOKUP(C28,[5]sheet1!$C:$J,6,0) -> 0 | O28: =H28+I28+J28+K28+L28+M28+N28 -> 5981.48 | P28: 5981.48 | Q28: 2 | R28: 575 | S28: 333 | T28: 22 | U28: 2 | V28: 0 | W28: 0 | X28: 0 | Y28: 0 | Z28: 451-499 | AA28: 412 | AB28: 381.86 | AC28: - | AD28: 438.37 | AE28: 2 | AF28: - | AG28: 763.72 | AH28: - | AI28: 348.01 | AJ28: - | AK28: 696.02 | AL28: - | AM28: 662 | AN28: 1 | AO28: 1 | AP28: 0.8689 | AQ28: 0.5369 | AR28: 0.9091 | AS28: 0.4545 | AT28: 0 | AU28: 0 | AV28: 0 | AW28: 0 | AX28: 0
A29: 9402310 | B29: 伯希和PELLIOT 经典1.0 户外运动修身高弹显瘦不闷热轻薄原纱凉感皮肤衣防紫外线舒适百搭防晒服 女款 | C29: 12421228 | D29: 伯希和/PELLIOT | E29: 女装-外套-防晒服 | F29: 一品多商 | G29: 品牌直发 | H29: 152 | I29: =VLOOKUP(C29,[6]sheet1!$C:$X,6,0) -> 774 | J29: =VLOOKUP(C29,[1]sheet1!$C:$I,6,0) -> 1008 | K29: =VLOOKUP(C29,[2]sheet1!$C:$H,6,0) -> 680 | L29: =VLOOKUP(C29,[3]sheet1!$C:$H,6,0) -> 581 | M29: =VLOOKUP(C29,[4]sheet1!$C:$I,6,0) -> 418 | N29: =VLOOKUP(C29,[5]sheet1!$C:$J,6,0) -> 259 | O29: =H29+I29+J29+K29+L29+M29+N29 -> 3872 | P29: 3872 | Q29: 1 | R29: 384 | S29: 353 | T29: 7 | U29: 1 | V29: 175 | W29: 2 | X29: 0 | Y29: 0 | Z29: 107-179 | AA29: 107 | AB29: 84.89 | AC29: - | AD29: 152 | AE29: 1 | AF29: - | AG29: 84.89 | AH29: - | AI29: - | AJ29: - | AK29: - | AL29: - | AM29: 455 | AN29: 1 | AO29: 0 | AP29: 0.6881 | AQ29: 0.4771 | AR29: 0.5714 | AS29: 0.7143 | AT29: 0 | AU29: 0 | AV29: 0 | AW29: 0 | AX29: 0
A30: 19692647 | B30: 伯希和PELLIOT 夏季东丽面料户外短袖原纱防晒抗菌运动上衣修身吸汗透气显瘦柔感亲肤半高领休闲内搭速干T恤 男款 | C30: 115215025 | D30: 伯希和/PELLIOT | E30: 服装-户外运动服-速干T恤 | F30: 一品多商 | G30: 品牌直发 | H30: 250 | I30: =VLOOKUP(C30,[6]sheet1!$C:$X,6,0) -> 0 | J30: =VLOOKUP(C30,[1]sheet1!$C:$I,6,0) -> 257 | K30: =VLOOKUP(C30,[2]sheet1!$C:$H,6,0) -> 0 | L30: =VLOOKUP(C30,[3]sheet1!$C:$H,6,0) -> 514 | M30: =VLOOKUP(C30,[4]sheet1!$C:$I,6,0) -> 250 | N30: =VLOOKUP(C30,[5]sheet1!$C:$J,6,0) -> 0 | O30: =H30+I30+J30+K30+L30+M30+N30 -> 1271 | P30: 1271 | Q30: 1 | R30: 1058 | S30: 127 | T30: 41 | U30: 1 | V30: 0 | W30: 0 | X30: 268 | Y30: 1 | Z30: 239-239 | AA30: 209 | AB30: 198.74 | AC30: - | AD30: 250 | AE30: 1 | AF30: - | AG30: 198.74 | AH30: - | AI30: 172.7 | AJ30: - | AK30: 172.7 | AL30: - | AM30: 1238 | AN30: 0 | AO30: 1 | AP30: 0.786 | AQ30: 0.3664 | AR30: 0.7073 | AS30: 0.4634 | AT30: 0 | AU30: 0 | AV30: 0 | AW30: 0 | AX30: 0
A31: 19624143 | B31: 伯希和PELLIOT 风盾 LT 系列 伯希和户外徒步登山裤CORDURA透气耐磨高弹运动裤跑步舒适休闲 软壳裤 男款 | C31: 115107003 | D31: 伯希和/PELLIOT | E31: 服装-长裤-软壳裤 | F31: 一品多商 | G31: 品牌直发 | H31: 501 | I31: =VLOOKUP(C31,[6]sheet1!$C:$X,6,0) -> 0 | J31: =VLOOKUP(C31,[1]sheet1!$C:$I,6,0) -> 1002 | K31: =VLOOKUP(C31,[2]sheet1!$C:$H,6,0) -> 2004 | L31: =VLOOKUP(C31,[3]sheet1!$C:$H,6,0) -> 974 | M31: =VLOOKUP(C31,[4]sheet1!$C:$I,6,0) -> 1498 | N31: =VLOOKUP(C31,[5]sheet1!$C:$J,6,0) -> 1483 | O31: =H31+I31+J31+K31+L31+M31+N31 -> 7462 | P31: 7462 | Q31: 1 | R31: 633 | S31: 215 | T31: 16 | U31: 1 | V31: 1529 | W31: 3 | X31: 0 | Y31: 0 | Z31: 550-550 | AA31: 429 | AB31: 467.49 | AC31: - | AD31: 501 | AE31: 1 | AF31: - | AG31: 467.49 | AH31: - | AI31: 362.46 | AJ31: - | AK31: 362.46 | AL31: - | AM31: 748 | AN31: 1 | AO31: 0 | AP31: 0.7939 | AQ31: 0.277 | AR31: 0.625 | AS31: 0.1875 | AT31: 0 | AU31: 0 | AV31: 0 | AW31: 0 | AX31: 0
A32: 19281735 | B32: 伯希和PELLIOT 山野 3.0 三合一运动户外舒适百搭通勤摇粒绒内胆腋下透气拉链 徒步 耐磨防水防风保暖冲锋衣 女款 | C32: 125301055 | D32: 伯希和/PELLIOT | E32: 女装-外套-冲锋衣 | F32: 一品多商 | G32: 品牌直发 | H32: 551 | I32: =VLOOKUP(C32,[6]sheet1!$C:$X,6,0) -> 1096 | J32: =VLOOKUP(C32,[1]sheet1!$C:$I,6,0) -> 548 | K32: =VLOOKUP(C32,[2]sheet1!$C:$H,6,0) -> 0 | L32: =VLOOKUP(C32,[3]sheet1!$C:$H,6,0) -> 0 | M32: =VLOOKUP(C32,[4]sheet1!$C:$I,6,0) -> 0 | N32: =VLOOKUP(C32,[5]sheet1!$C:$J,6,0) -> 0 | O32: =H32+I32+J32+K32+L32+M32+N32 -> 2195 | P32: 2195 | Q32: 1 | R32: 403 | S32: 335 | T32: 5 | U32: 1 | V32: 0 | W32: 0 | X32: 0 | Y32: 0 | Z32: 590-599 | AA32: 537 | AB32: 500.73 | AC32: - | AD32: 551 | AE32: 1 | AF32: - | AG32: 500.73 | AH32: - | AI32: 454.73 | AJ32: - | AK32: 454.73 | AL32: - | AM32: 457 | AN32: 1 | AO32: 1 | AP32: 0.9083 | AQ32: 0.625 | AR32: 1 | AS32: 0.6 | AT32: 0 | AU32: 0 | AV32: 0 | AW32: 0 | AX32: 0
A33: 14617186 | B33: 伯希和PELLIOT 岩壳PRO 硬壳单冲升级RECCO防暴雨透气宽松户外专业全防护登山服时尚耐磨 冲锋衣 男女同款 | C33: 124301070 | D33: 伯希和/PELLIOT | E33: 服装-外套-冲锋衣 | F33: 一品多商 | G33: 品牌直发 | H33: 815 | I33: =VLOOKUP(C33,[6]sheet1!$C:$X,6,0) -> 0 | J33: =VLOOKUP(C33,[1]sheet1!$C:$I,6,0) -> 0 | K33: =VLOOKUP(C33,[2]sheet1!$C:$H,6,0) -> 801 | L33: =VLOOKUP(C33,[3]sheet1!$C:$H,6,0) -> 0 | M33: =VLOOKUP(C33,[4]sheet1!$C:$I,6,0) -> 1592 | N33: =VLOOKUP(C33,[5]sheet1!$C:$J,6,0) -> 808 | O33: =H33+I33+J33+K33+L33+M33+N33 -> 4016 | P33: 4016 | Q33: 1 | R33: 1158 | S33: 116 | T33: 55 | U33: 1 | V33: 0 | W33: 0 | X33: 0 | Y33: 0 | Z33: 833-890 | AA33: 660 | AB33: 713.43 | AC33: - | AD33: 815 | AE33: 1 | AF33: - | AG33: 713.43 | AH33: - | AI33: 596.27 | AJ33: - | AK33: 596.27 | AL33: - | AM33: 1409 | AN33: 1 | AO33: 1 | AP33: 0.8838 | AQ33: 0.5596 | AR33: 0.8364 | AS33: 0.5636 | AT33: 0 | AU33: 0 | AV33: 0 | AW33: 0 | AX33: 0
A34: 14143668 | B34: 伯希和PELLIOT 经典1.0 风盾C24 户外加绒保暖防风防泼水登山徒步耐磨运动跑步透气舒适高弹连帽夹克外套 软壳衣 男款 | C34: 114306147 | D34: 伯希和/PELLIOT | E34: 服装-外套-软壳衣 | F34: 一品多商 | G34: 品牌直发 | H34: 437 | I34: =VLOOKUP(C34,[6]sheet1!$C:$X,6,0) -> 0 | J34: =VLOOKUP(C34,[1]sheet1!$C:$I,6,0) -> 451 | K34: =VLOOKUP(C34,[2]sheet1!$C:$H,6,0) -> 0 | L34: =VLOOKUP(C34,[3]sheet1!$C:$H,6,0) -> 0 | M34: =VLOOKUP(C34,[4]sheet1!$C:$I,6,0) -> 902 | N34: =VLOOKUP(C34,[5]sheet1!$C:$J,6,0) -> 899 | O34: =H34+I34+J34+K34+L34+M34+N34 -> 2689 | P34: 2689 | Q34: 1 | R34: 981 | S34: 138 | T34: 42 | U34: 1 | V34: 0 | W34: 0 | X34: 0 | Y34: 0 | Z34: 409-490 | AA34: 299 | AB34: 344.8 | AC34: - | AD34: 437 | AE34: 1 | AF34: - | AG34: 344.8 | AH34: - | AI34: 252.31 | AJ34: - | AK34: 252.31 | AL34: - | AM34: 1082 | AN34: 1 | AO34: 1 | AP34: 0.8706 | AQ34: 0.4923 | AR34: 0.9048 | AS34: 0.4524 | AT34: 0 | AU34: 0 | AV34: 0 | AW34: 0 | AX34: 0
A35: 10851829 | B35: 伯希和PELLIOT 山野 户外运动机能通勤登山徒步抓绒内胆可拆卸三合一外套 冲锋衣 男女同款 | C35: 11340105-CF05 | D35: 伯希和/PELLIOT | E35: 服装-外套-冲锋衣 | F35: 一品多商 | G35: 品牌直发 | H35: 453 | I35: =VLOOKUP(C35,[6]sheet1!$C:$X,6,0) -> 1279 | J35: =VLOOKUP(C35,[1]sheet1!$C:$I,6,0) -> 3006.3 | K35: =VLOOKUP(C35,[2]sheet1!$C:$H,6,0) -> 423 | L35: 0 | M35: 0 | N35: =VLOOKUP(C35,[5]sheet1!$C:$J,6,0) -> 0 | O35: =H35+I35+J35+K35+L35+M35+N35 -> 5161.3 | P35: 5161.3 | Q35: 1 | R35: 767 | S35: 176 | T35: 28 | U35: 1 | V35: 0 | W35: 0 | X35: 0 | Y35: 0 | Z35: 441-464 | AA35: 420 | AB35: 373.18 | AC35: - | AD35: 453 | AE35: 1 | AF35: - | AG35: 373.18 | AH35: - | AI35: 359.15 | AJ35: - | AK35: 359.15 | AL35: - | AM35: 904 | AN35: 1 | AO35: 1 | AP35: 0.8759 | AQ35: 0.5333 | AR35: 0.8929 | AS35: 0.5714 | AT35: 0 | AU35: 0 | AV35: 0 | AW35: 0 | AX35: 0
A36: 9985207 | B36: 伯希和PELLIOT 经典1.0 户外高弹防刮耐磨透气舒适跑步运动裤CORDURA®科技面料可拆卸登山裤两截裤速干裤 男款 | C36: 11421415 | D36: 伯希和/PELLIOT | E36: 服装-户外运动服-速干裤 | F36: 一品多商 | G36: 品牌直发 | H36: 0 | I36: =VLOOKUP(C36,[6]sheet1!$C:$X,6,0) -> 1085 | J36: =VLOOKUP(C36,[1]sheet1!$C:$I,6,0) -> 0 | K36: =VLOOKUP(C36,[2]sheet1!$C:$H,6,0) -> 442 | L36: =VLOOKUP(C36,[3]sheet1!$C:$H,6,0) -> 228.6 | M36: =VLOOKUP(C36,[4]sheet1!$C:$I,6,0) -> 915 | N36: =VLOOKUP(C36,[5]sheet1!$C:$J,6,0) -> 221 | O36: =H36+I36+J36+K36+L36+M36+N36 -> 2891.6 | P36: 2891.6 | Q36: 0 | R36: 1505 | S36: 0 | T36: 78 | U36: 0 | V36: 485.6 | W36: 2 | X36: 0 | Y36: 0 | Z36: 214-214 | AA36: 201 | AB36: 176.94 | AC36: - | AD36: 0 | AE36: 0 | AF36: - | AG36: 0 | AH36: - | AI36: 165.66 | AJ36: - | AK36: 0 | AL36: - | AM36: 1743 | AN36: 0 | AO36: 0 | AP36: 0.8513 | AQ36: 0.4725 | AR36: 0.8974 | AS36: 0.5641 | AT36: 0 | AU36: 0 | AV36: 0 | AW36: 0 | AX36: 0
A37: 9742964 | B37: 伯希和PELLIOT 户外运动冰丝防晒直筒UPF50+高弹钓鱼跑步吸湿轻薄舒适百搭透气速干裤 男款 | C37: 11421409 | D37: 伯希和/PELLIOT | E37: 服装-户外运动服-速干裤 | F37: 一品多商 | G37: 品牌直发 | H37: 0 | I37: =VLOOKUP(C37,[6]sheet1!$C:$X,6,0) -> 0 | J37: =VLOOKUP(C37,[1]sheet1!$C:$I,6,0) -> 0 | K37: =VLOOKUP(C37,[2]sheet1!$C:$H,6,0) -> 0 | L37: =VLOOKUP(C37,[3]sheet1!$C:$H,6,0) -> 0 | M37: =VLOOKUP(C37,[4]sheet1!$C:$I,6,0) -> 0 | N37: =VLOOKUP(C37,[5]sheet1!$C:$J,6,0) -> 0 | O37: =H37+I37+J37+K37+L37+M37+N37 -> 0 | P37: 0 | Q37: 0 | R37: 308 | S37: 0 | T37: 5 | U37: 0 | V37: 0 | W37: 0 | X37: 0 | Y37: 0 | Z37: - | AA37: 155 | AB37: - | AC37: - | AD37: 0 | AE37: 0 | AF37: - | AG37: - | AH37: - | AI37: 125.73 | AJ37: - | AK37: 0 | AL37: - | AM37: 360 | AN37: 0 | AO37: 0 | AP37: 0.6571 | AQ37: 0.2571 | AR37: 0.6 | AS37: 0.2 | AT37: 0 | AU37: 0 | AV37: 0 | AW37: 0 | AX37: 0
A38: 9423402 | B38: 伯希和PELLIOT 经典1.0 轻风 防紫外线户外运动连帽轻量透气UPF50+ 专业皮肤衣轻薄防泼水多巴胺衣服防晒服 女款 | C38: 12421250 | D38: 伯希和/PELLIOT | E38: 女装-外套-防晒服 | F38: 一品多商 | G38: 品牌直发 | H38: 0 | I38: =VLOOKUP(C38,[6]sheet1!$C:$X,6,0) -> 0 | J38: =VLOOKUP(C38,[1]sheet1!$C:$I,6,0) -> 0 | K38: =VLOOKUP(C38,[2]sheet1!$C:$H,6,0) -> 0 | L38: =VLOOKUP(C38,[3]sheet1!$C:$H,6,0) -> 0 | M38: =VLOOKUP(C38,[4]sheet1!$C:$I,6,0) -> 0 | N38: =VLOOKUP(C38,[5]sheet1!$C:$J,6,0) -> 0 | O38: =H38+I38+J38+K38+L38+M38+N38 -> 0 | P38: 0 | Q38: 0 | R38: 1004 | S38: 0 | T38: 54 | U38: 0 | V38: 0 | W38: 0 | X38: 0 | Y38: 0 | Z38: 259-259 | AA38: 229 | AB38: 216.82 | AC38: - | AD38: 0 | AE38: 0 | AF38: - | AG38: 0 | AH38: - | AI38: 190.78 | AJ38: - | AK38: 0 | AL38: - | AM38: 1084 | AN38: 0 | AO38: 0 | AP38: 0.8913 | AQ38: 0.4268 | AR38: 0.9259 | AS38: 0.5 | AT38: 0 | AU38: 0 | AV38: 0 | AW38: 0 | AX38: 0
A39: 9414196 | B39: 伯希和PELLIOT 经典1.0 轻风 UPF50+户外轻量专业皮肤衣轻薄防泼水多巴胺防晒服 男女同款 | C39: 11421201 | D39: 伯希和/PELLIOT | E39: 服装-外套-防晒服 | F39: 一品多商 | G39: 品牌直发 | H39: 0 | I39: =VLOOKUP(C39,[6]sheet1!$C:$X,6,0) -> 2849.36 | J39: =VLOOKUP(C39,[1]sheet1!$C:$I,6,0) -> 2018 | K39: =VLOOKUP(C39,[2]sheet1!$C:$H,6,0) -> 2863 | L39: =VLOOKUP(C39,[3]sheet1!$C:$H,6,0) -> 2116 | M39: =VLOOKUP(C39,[4]sheet1!$C:$I,6,0) -> 2158 | N39: =VLOOKUP(C39,[5]sheet1!$C:$J,6,0) -> 2254.17 | O39: =H39+I39+J39+K39+L39+M39+N39 -> 14258.53 | P39: 14258.53 | Q39: 0 | R39: 1194 | S39: 0 | T39: 44 | U39: 0 | V39: 772 | W39: 4 | X39: 0 | Y39: 0 | Z39: 259-259 | AA39: 209 | AB39: 217.3 | AC39: - | AD39: 0 | AE39: 0 | AF39: - | AG39: 0 | AH39: - | AI39: 173.9 | AJ39: - | AK39: 0 | AL39: - | AM39: 1449 | AN39: 0 | AO39: 0 | AP39: 0.7922 | AQ39: 0.5028 | AR39: 0.7727 | AS39: 0.5 | AT39: 0 | AU39: 0 | AV39: 0 | AW39: 0 | AX39: 0
A40: 9077745 | B40: 伯希和PELLIOT 经典1.0 户外运动跑步登山徒步速干短袖抗菌轻弹休闲百搭柔软亲肤舒适Polo衫 女款 | C40: 12421534 | D40: 伯希和/PELLIOT | E40: 女装-上衣-Polo衫 | F40: 一品多商 | G40: 品牌直发 | H40: 0 | I40: =VLOOKUP(C40,[6]sheet1!$C:$X,6,0) -> 0 | J40: =VLOOKUP(C40,[1]sheet1!$C:$I,6,0) -> 0 | K40: =VLOOKUP(C40,[2]sheet1!$C:$H,6,0) -> 0 | L40: =VLOOKUP(C40,[3]sheet1!$C:$H,6,0) -> 0 | M40: =VLOOKUP(C40,[4]sheet1!$C:$I,6,0) -> 0 | N40: =VLOOKUP(C40,[5]sheet1!$C:$J,6,0) -> 474 | O40: =H40+I40+J40+K40+L40+M40+N40 -> 474 | P40: 474 | Q40: 0 | R40: 874 | S40: 0 | T40: 10 | U40: 0 | V40: 0 | W40: 0 | X40: 0 | Y40: 0 | Z40: 241-269 | AA40: 229 | AB40: 199.5 | AC40: - | AD40: 0 | AE40: 0 | AF40: - | AG40: 0 | AH40: - | AI40: 189.08 | AJ40: - | AK40: 0 | AL40: - | AM40: 973 | AN40: 0 | AO40: 0 | AP40: 0.8248 | AQ40: 0.2265 | AR40: 0.5 | AS40: 0.2 | AT40: 0 | AU40: 0 | AV40: 0 | AW40: 0 | AX40: 0
A41: 8568910 | B41: 伯希和PELLIOT 经典1.0 小森林CT 轻薄透气衣户外运动徒步UPF50+防紫外线皮肤衣可收纳轻量化舒适百搭 超轻速干防晒服 女款 | C41: 12421254 | D41: 伯希和/PELLIOT | E41: 女装-外套-防晒服 | F41: 一品多商 | G41: 品牌直发 | H41: 0 | I41: =VLOOKUP(C41,[6]sheet1!$C:$X,6,0) -> 0 | J41: =VLOOKUP(C41,[1]sheet1!$C:$I,6,0) -> 0 | K41: =VLOOKUP(C41,[2]sheet1!$C:$H,6,0) -> 0 | L41: =VLOOKUP(C41,[3]sheet1!$C:$H,6,0) -> 0 | M41: =VLOOKUP(C41,[4]sheet1!$C:$I,6,0) -> 0 | N41: =VLOOKUP(C41,[5]sheet1!$C:$J,6,0) -> 0 | O41: =H41+I41+J41+K41+L41+M41+N41 -> 0 | P41: 0 | Q41: 0 | R41: 617 | S41: 0 | T41: 9 | U41: 0 | V41: 0 | W41: 0 | X41: 0 | Y41: 0 | Z41: 241-249 | AA41: 241 | AB41: 201.2 | AC41: - | AD41: 0 | AE41: 0 | AF41: - | AG41: 0 | AH41: - | AI41: - | AJ41: - | AK41: - | AL41: - | AM41: 661 | AN41: 0 | AO41: 0 | AP41: 0.9075 | AQ41: 0.2349 | AR41: 0.8889 | AS41: 0.3333 | AT41: 0 | AU41: 0 | AV41: 0 | AW41: 0 | AX41: 0
A42: 8470818 | B42: 伯希和PELLIOT 玫瑰山壳硬壳百搭宽松防风防水运动跑步登山服全天候三层压胶工艺 冲锋衣 男女同款 | C42: 12340164-新加色 | D42: 伯希和/PELLIOT | E42: 服装-外套-冲锋衣 | F42: 一品多商 | G42: 品牌直发 | H42: 0 | I42: =VLOOKUP(C42,[6]sheet1!$C:$X,6,0) -> 636 | J42: =VLOOKUP(C42,[1]sheet1!$C:$I,6,0) -> 0 | K42: =VLOOKUP(C42,[2]sheet1!$C:$H,6,0) -> 1926 | L42: =VLOOKUP(C42,[3]sheet1!$C:$H,6,0) -> 0 | M42: =VLOOKUP(C42,[4]sheet1!$C:$I,6,0) -> 0 | N42: =VLOOKUP(C42,[5]sheet1!$C:$J,6,0) -> 0 | O42: =H42+I42+J42+K42+L42+M42+N42 -> 2562 | P42: 2562 | Q42: 0 | R42: 749 | S42: 0 | T42: 24 | U42: 0 | V42: 0 | W42: 0 | X42: 0 | Y42: 0 | Z42: 656-699 | AA42: 597 | AB42: 559.8 | AC42: - | AD42: 0 | AE42: 0 | AF42: - | AG42: 0 | AH42: - | AI42: 532.47 | AJ42: - | AK42: 0 | AL42: - | AM42: 857 | AN42: 0 | AO42: 0 | AP42: 0.8651 | AQ42: 0.4867 | AR42: 0.9167 | AS42: 0.4167 | AT42: 0 | AU42: 0 | AV42: 0 | AW42: 0 | AX42: 0
A43: 6415357 | B43: 伯希和PELLIOT 经典1.0 极光MAX 700蓬加长加厚防风御寒鹅绒百搭舒适保暖连帽长款羽绒服 女款 | C43: 12340806 | D43: 伯希和/PELLIOT | E43: 女装-外套-羽绒服 | F43: 一品多商 | G43: 品牌直发 | H43: 0 | I43: =VLOOKUP(C43,[6]sheet1!$C:$X,6,0) -> 0 | J43: =VLOOKUP(C43,[1]sheet1!$C:$I,6,0) -> 0 | K43: =VLOOKUP(C43,[2]sheet1!$C:$H,6,0) -> 0 | L43: =VLOOKUP(C43,[3]sheet1!$C:$H,6,0) -> 0 | M43: =VLOOKUP(C43,[4]sheet1!$C:$I,6,0) -> 0 | N43: =VLOOKUP(C43,[5]sheet1!$C:$J,6,0) -> 0 | O43: =H43+I43+J43+K43+L43+M43+N43 -> 0 | P43: 0 | Q43: 0 | R43: 851 | S43: 0 | T43: 18 | U43: 0 | V43: 0 | W43: 0 | X43: 0 | Y43: 0 | Z43: 1574-1790 | AA43: 1398 | AB43: 1354.74 | AC43: - | AD43: 0 | AE43: 0 | AF43: - | AG43: 0 | AH43: - | AI43: 1201.97 | AJ43: - | AK43: 0 | AL43: - | AM43: 936 | AN43: 0 | AO43: 0 | AP43: 0.9421 | AQ43: 0.6935 | AR43: 0.9444 | AS43: 0.5 | AT43: 0 | AU43: 0 | AV43: 0 | AW43: 0 | AX43: 0
A44: 5913475 | B44: 伯希和PELLIOT 经典1.0 户外运动防水防风登山服徒步夹克外套中长款收腰显瘦旅行休闲风衣 软壳衣 女款 | C44: 12330602 | D44: 伯希和/PELLIOT | E44: 女装-外套-软壳衣 | F44: 一品多商 | G44: 品牌直发 | H44: 0 | I44: =VLOOKUP(C44,[6]sheet1!$C:$X,6,0) -> 0 | J44: =VLOOKUP(C44,[1]sheet1!$C:$I,6,0) -> 361 | K44: =VLOOKUP(C44,[2]sheet1!$C:$H,6,0) -> 361 | L44: =VLOOKUP(C44,[3]sheet1!$C:$H,6,0) -> 0 | M44: =VLOOKUP(C44,[4]sheet1!$C:$I,6,0) -> 0 | N44: =VLOOKUP(C44,[5]sheet1!$C:$J,6,0) -> 0 | O44: =H44+I44+J44+K44+L44+M44+N44 -> 722 | P44: 722 | Q44: 0 | R44: 323 | S44: 0 | T44: 4 | U44: 0 | V44: 0 | W44: 0 | X44: 0 | Y44: 0 | Z44: 389-399 | AA44: 296 | AB44: 325.46 | AC44: - | AD44: 0 | AE44: 0 | AF44: - | AG44: 0 | AH44: - | AI44: 244.74 | AJ44: - | AK44: 0 | AL44: - | AM44: 353 | AN44: 0 | AO44: 0 | AP44: 0.9091 | AQ44: 0.4156 | AR44: 1 | AS44: 0.75 | AT44: 0 | AU44: 0 | AV44: 0 | AW44: 0 | AX44: 0
A45: 4461555 | B45: 伯希和PELLIOT 经典1.0 城市户外运动吸湿排汗快干裤弹力轻薄柔软亲肤透气登山通勤百搭束脚长裤徒步休闲裤 男款 | C45: 11121411 | D45: 伯希和/PELLIOT | E45: 服装-户外运动服-速干裤 | F45: 一品多商 | G45: 品牌直发 | H45: 0 | I45: =VLOOKUP(C45,[6]sheet1!$C:$X,6,0) -> 0 | J45: =VLOOKUP(C45,[1]sheet1!$C:$I,6,0) -> 0 | K45: =VLOOKUP(C45,[2]sheet1!$C:$H,6,0) -> 0 | L45: =VLOOKUP(C45,[3]sheet1!$C:$H,6,0) -> 0 | M45: =VLOOKUP(C45,[4]sheet1!$C:$I,6,0) -> 0 | N45: =VLOOKUP(C45,[5]sheet1!$C:$J,6,0) -> 0 | O45: =H45+I45+J45+K45+L45+M45+N45 -> 0 | P45: 0 | Q45: 0 | R45: 401 | S45: 0 | T45: 2 | U45: 0 | V45: 0 | W45: 0 | X45: 0 | Y45: 0 | Z45: - | AA45: 178 | AB45: - | AC45: - | AD45: 0 | AE45: 0 | AF45: - | AG45: - | AH45: - | AI45: 145.69 | AJ45: - | AK45: 0 | AL45: - | AM45: 454 | AN45: 0 | AO45: 0 | AP45: 0.6555 | AQ45: 0.1765 | AR45: 0.5 | AS45: 1 | AT45: 0 | AU45: 0 | AV45: 0 | AW45: 0 | AX45: 0
A46: 4460489 | B46: 伯希和PELLIOT 经典1.0 户外薄款登山徒步直筒高弹力清爽轻薄长裤专业防泼水耐磨透气运动跑步速干裤 男款 | C46: 11321405 | D46: 伯希和/PELLIOT | E46: 服装-户外运动服-速干裤 | F46: 一品多商 | G46: 品牌直发 | H46: 0 | I46: =VLOOKUP(C46,[6]sheet1!$C:$X,6,0) -> 0 | J46: =VLOOKUP(C46,[1]sheet1!$C:$I,6,0) -> 0 | K46: =VLOOKUP(C46,[2]sheet1!$C:$H,6,0) -> 0 | L46: =VLOOKUP(C46,[3]sheet1!$C:$H,6,0) -> 0 | M46: =VLOOKUP(C46,[4]sheet1!$C:$I,6,0) -> 0 | N46: =VLOOKUP(C46,[5]sheet1!$C:$J,6,0) -> 0 | O46: =H46+I46+J46+K46+L46+M46+N46 -> 0 | P46: 0 | Q46: 0 | R46: 1301 | S46: 0 | T46: 46 | U46: 0 | V46: 0 | W46: 0 | X46: 0 | Y46: 0 | Z46: 273-299 | AA46: 250 | AB46: 228.15 | AC46: - | AD46: 0 | AE46: 0 | AF46: - | AG46: 0 | AH46: - | AI46: 218.19 | AJ46: - | AK46: 0 | AL46: - | AM46: 1433 | AN46: 0 | AO46: 0 | AP46: 0.94 | AQ46: 0.6483 | AR46: 0.913 | AS46: 0.7174 | AT46: 0 | AU46: 0 | AV46: 0 | AW46: 0 | AX46: 0
A47: 4460199 | B47: 伯希和PELLIOT 城市户外系列UPF50+宽松弹力显瘦阔腿裤垂感透气百搭高腰束脚防晒休闲裤 女款 | C47: 12321414 | D47: 伯希和/PELLIOT | E47: 女装-户外运动服-速干裤 | F47: 一品一商 | G47: 品牌直发 | H47: 0 | I47: =VLOOKUP(C47,[6]sheet1!$C:$X,6,0) -> 0 | J47: =VLOOKUP(C47,[1]sheet1!$C:$I,6,0) -> 127 | K47: =VLOOKUP(C47,[2]sheet1!$C:$H,6,0) -> 124 | L47: =VLOOKUP(C47,[3]sheet1!$C:$H,6,0) -> 0 | M47: =VLOOKUP(C47,[4]sheet1!$C:$I,6,0) -> 0 | N47: =VLOOKUP(C47,[5]sheet1!$C:$J,6,0) -> 0 | O47: =H47+I47+J47+K47+L47+M47+N47 -> 251 | P47: 251 | Q47: 0 | R47: 89 | S47: 0 | T47: 3 | U47: 0 | V47: 0 | W47: 0 | X47: 0 | Y47: 0 | Z47: - | AA47: - | AB47: - | AC47: - | AD47: 0 | AE47: 0 | AF47: - | AG47: - | AH47: - | AI47: - | AJ47: - | AK47: - | AL47: - | AM47: 110 | AN47: 0 | AO47: 0 | AP47: 0.6966 | AQ47: 0.2697 | AR47: 0.6667 | AS47: 0.3333 | AT47: 0 | AU47: 0 | AV47: 0 | AW47: 0 | AX47: 0
A48: 3662675 | B48: 伯希和PELLIOT 经典1.0 风盾时尚轻便耐磨加绒保暖高弹运动夹克透气舒适休闲百搭外套 软壳衣 女款 | C48: 12230602 | D48: 伯希和/PELLIOT | E48: 女装-外套-软壳衣 | F48: 一品多商 | G48: 品牌直发 | H48: 0 | I48: =VLOOKUP(C48,[6]sheet1!$C:$X,6,0) -> 0 | J48: =VLOOKUP(C48,[1]sheet1!$C:$I,6,0) -> 0 | K48: =VLOOKUP(C48,[2]sheet1!$C:$H,6,0) -> 0 | L48: =VLOOKUP(C48,[3]sheet1!$C:$H,6,0) -> 0 | M48: =VLOOKUP(C48,[4]sheet1!$C:$I,6,0) -> 0 | N48: =VLOOKUP(C48,[5]sheet1!$C:$J,6,0) -> 0 | O48: =H48+I48+J48+K48+L48+M48+N48 -> 0 | P48: 0 | Q48: 0 | R48: 482 | S48: 0 | T48: 7 | U48: 0 | V48: 0 | W48: 0 | X48: 0 | Y48: 0 | Z48: 379-379 | AA48: 314 | AB48: 316.78 | AC48: - | AD48: 0 | AE48: 0 | AF48: - | AG48: 0 | AH48: - | AI48: 260.36 | AJ48: - | AK48: 0 | AL48: - | AM48: 529 | AN48: 0 | AO48: 0 | AP48: 0.8953 | AQ48: 0.7267 | AR48: 1 | AS48: 0.8571 | AT48: 0 | AU48: 0 | AV48: 0 | AW48: 0 | AX48: 0
A49: 3662670 | B49: 伯希和PELLIOT 经典1.0系列 风盾 户外运动跑步徒步登山日常通勤开衫加绒高弹轻便耐磨外套时尚休闲舒适百搭夹克卫衣 软壳衣 男款 | C49: 11230601 | D49: 伯希和/PELLIOT | E49: 服装-外套-软壳衣 | F49: 一品多商 | G49: 品牌直发 | H49: 0 | I49: =VLOOKUP(C49,[6]sheet1!$C:$X,6,0) -> 0 | J49: =VLOOKUP(C49,[1]sheet1!$C:$I,6,0) -> 0 | K49: =VLOOKUP(C49,[2]sheet1!$C:$H,6,0) -> 0 | L49: =VLOOKUP(C49,[3]sheet1!$C:$H,6,0) -> 0 | M49: =VLOOKUP(C49,[4]sheet1!$C:$I,6,0) -> 0 | N49: =VLOOKUP(C49,[5]sheet1!$C:$J,6,0) -> 0 | O49: =H49+I49+J49+K49+L49+M49+N49 -> 0 | P49: 0 | Q49: 0 | R49: 920 | S49: 0 | T49: 45 | U49: 0 | V49: 0 | W49: 0 | X49: 0 | Y49: 0 | Z49: - | AA49: 318 | AB49: - | AC49: - | AD49: 0 | AE49: 0 | AF49: - | AG49: - | AH49: - | AI49: 265.81 | AJ49: - | AK49: 0 | AL49: - | AM49: 1050 | AN49: 0 | AO49: 0 | AP49: 0.7728 | AQ49: 0.3664 | AR49: 0.6889 | AS49: 0.2444 | AT49: 0 | AU49: 0 | AV49: 0 | AW49: 0 | AX49: 0
A50: 3556777 | B50: 伯希和PELLIOT 经典2.0 户外保暖防风保温亲肤内胆羊羔绒摇粒绒运动旅行舒适百搭穿搭开衫立领抓绒衣 男款 | C50: 115110021 | D50: 伯希和/PELLIOT | E50: 服装-户外运动服-抓绒衣 | F50: 一品多商 | G50: 品牌直发 | H50: 0 | I50: =VLOOKUP(C50,[6]sheet1!$C:$X,6,0) -> 0 | J50: =VLOOKUP(C50,[1]sheet1!$C:$I,6,0) -> 0 | K50: =VLOOKUP(C50,[2]sheet1!$C:$H,6,0) -> 0 | L50: =VLOOKUP(C50,[3]sheet1!$C:$H,6,0) -> 0 | M50: =VLOOKUP(C50,[4]sheet1!$C:$I,6,0) -> 0 | N50: =VLOOKUP(C50,[5]sheet1!$C:$J,6,0) -> 0 | O50: =H50+I50+J50+K50+L50+M50+N50 -> 0 | P50: 0 | Q50: 0 | R50: 391 | S50: 0 | T50: 17 | U50: 0 | V50: 0 | W50: 0 | X50: 0 | Y50: 0 | Z50: 239-239 | AA50: 214 | AB50: 197.64 | AC50: - | AD50: 0 | AE50: 0 | AF50: - | AG50: 0 | AH50: - | AI50: 175.94 | AJ50: - | AK50: 0 | AL50: - | AM50: 491 | AN50: 0 | AO50: 0 | AP50: 0.8407 | AQ50: 0.5929 | AR50: 1 | AS50: 0.5294 | AT50: 0 | AU50: 0 | AV50: 0 | AW50: 0 | AX50: 0
A51: 3268431 | B51: 伯希和PELLIOT 山海户外露营登山徒步滑雪服装防风防水三合一内胆可拆卸连帽 冲锋衣 男女同款 | C51: 112240128 | D51: 伯希和/PELLIOT | E51: 服装-外套-冲锋衣 | F51: 一品多商 | G51: 品牌直发 | H51: 0 | I51: =VLOOKUP(C51,[6]sheet1!$C:$X,6,0) -> 0 | J51: =VLOOKUP(C51,[1]sheet1!$C:$I,6,0) -> 0 | K51: =VLOOKUP(C51,[2]sheet1!$C:$H,6,0) -> 0 | L51: =VLOOKUP(C51,[3]sheet1!$C:$H,6,0) -> 928 | M51: =VLOOKUP(C51,[4]sheet1!$C:$I,6,0) -> 0 | N51: =VLOOKUP(C51,[5]sheet1!$C:$J,6,0) -> 0 | O51: =H51+I51+J51+K51+L51+M51+N51 -> 928 | P51: 928 | Q51: 0 | R51: 539 | S51: 0 | T51: 9 | U51: 0 | V51: 0 | W51: 0 | X51: 0 | Y51: 0 | Z51: 900-959 | AA51: 581 | AB51: 771.59 | AC51: - | AD51: 0 | AE51: 0 | AF51: - | AG51: 0 | AH51: - | AI51: 494.7 | AJ51: - | AK51: 0 | AL51: - | AM51: 638 | AN51: 0 | AO51: 0 | AP51: 0.7488 | AQ51: 0.4512 | AR51: 1 | AS51: 0.4444 | AT51: 0 | AU51: 0 | AV51: 0 | AW51: 0 | AX51: 0
A52: 3178778 | B52: 伯希和PELLIOT 经典1.0 山色经典款户外登山机能滑雪服科技透湿系统保暖连帽三合一抓绒内胆 徒步 防水防风透气耐磨冲锋衣 男款 | C52: 11040105 | D52: 伯希和/PELLIOT | E52: 服装-外套-冲锋衣 | F52: 一品多商 | G52: 品牌直发 | H52: 0 | I52: =VLOOKUP(C52,[6]sheet1!$C:$X,6,0) -> 0 | J52: =VLOOKUP(C52,[1]sheet1!$C:$I,6,0) -> 0 | K52: =VLOOKUP(C52,[2]sheet1!$C:$H,6,0) -> 0 | L52: =VLOOKUP(C52,[3]sheet1!$C:$H,6,0) -> 0 | M52: =VLOOKUP(C52,[4]sheet1!$C:$I,6,0) -> 941 | N52: =VLOOKUP(C52,[5]sheet1!$C:$J,6,0) -> 0 | O52: =H52+I52+J52+K52+L52+M52+N52 -> 941 | P52: 941 | Q52: 0 | R52: 487 | S52: 0 | T52: 17 | U52: 0 | V52: 0 | W52: 0 | X52: 0 | Y52: 0 | Z52: 599-599 | AA52: 469 | AB52: 510.32 | AC52: - | AD52: 0 | AE52: 0 | AF52: - | AG52: 0 | AH52: - | AI52: 397.48 | AJ52: - | AK52: 0 | AL52: - | AM52: 555 | AN52: 0 | AO52: 0 | AP52: 0.9257 | AQ52: 0.3543 | AR52: 1 | AS52: 0.3529 | AT52: 0 | AU52: 0 | AV52: 0 | AW52: 0 | AX52: 0
A53: 3178777 | B53: 伯希和PELLIOT 经典1.0 山色收腰防水防风保暖登山徒步滑雪旅行三合一可拆卸抓绒内胆透气耐磨 冲锋衣 女款 | C53: 12040106 | D53: 伯希和/PELLIOT | E53: 女装-外套-冲锋衣 | F53: 一品多商 | G53: 品牌直发 | H53: 0 | I53: =VLOOKUP(C53,[6]sheet1!$C:$X,6,0) -> 0 | J53: =VLOOKUP(C53,[1]sheet1!$C:$I,6,0) -> 0 | K53: =VLOOKUP(C53,[2]sheet1!$C:$H,6,0) -> 0 | L53: =VLOOKUP(C53,[3]sheet1!$C:$H,6,0) -> 0 | M53: =VLOOKUP(C53,[4]sheet1!$C:$I,6,0) -> 0 | N53: =VLOOKUP(C53,[5]sheet1!$C:$J,6,0) -> 1069 | O53: =H53+I53+J53+K53+L53+M53+N53 -> 1069 | P53: 1069 | Q53: 0 | R53: 539 | S53: 0 | T53: 5 | U53: 0 | V53: 0 | W53: 0 | X53: 0 | Y53: 0 | Z53: 599-599 | AA53: 480 | AB53: 508.54 | AC53: - | AD53: 0 | AE53: 0 | AF53: - | AG53: 0 | AH53: - | AI53: 405.25 | AJ53: - | AK53: 0 | AL53: - | AM53: 599 | AN53: 0 | AO53: 0 | AP53: 0.8884 | AQ53: 0.3581 | AR53: 0.8 | AS53: 0.4 | AT53: 0 | AU53: 0 | AV53: 0 | AW53: 0 | AX53: 0
A54: 21376537 | B54: 伯希和PELLIOT 户外运动薄款原纱型吸湿时尚简约纯色防晒上衣跑步休闲弹力透气舒适速干短袖百搭Polo衫 女款 | C54: 125215020 | D54: 伯希和/PELLIOT | E54: 女装-上衣-Polo衫 | F54: 一品多商 | G54: 品牌直发 | H54: 0 | I54: =VLOOKUP(C54,[6]sheet1!$C:$X,6,0) -> 0 | J54: =VLOOKUP(C54,[1]sheet1!$C:$I,6,0) -> 0 | K54: =VLOOKUP(C54,[2]sheet1!$C:$H,6,0) -> 0 | L54: =VLOOKUP(C54,[3]sheet1!$C:$H,6,0) -> 0 | M54: =VLOOKUP(C54,[4]sheet1!$C:$I,6,0) -> 0 | N54: =VLOOKUP(C54,[5]sheet1!$C:$J,6,0) -> 0 | O54: =H54+I54+J54+K54+L54+M54+N54 -> 0 | P54: 0 | Q54: 0 | R54: 616 | S54: 0 | T54: 24 | U54: 0 | V54: 0 | W54: 0 | X54: 0 | Y54: 0 | Z54: - | AA54: 173 | AB54: - | AC54: - | AD54: 0 | AE54: 0 | AF54: - | AG54: - | AH54: - | AI54: 140.47 | AJ54: - | AK54: 0 | AL54: - | AM54: 696 | AN54: 0 | AO54: 0 | AP54: 0.8786 | AQ54: 0.6071 | AR54: 0.9167 | AS54: 0.625 | AT54: 0 | AU54: 0 | AV54: 0 | AW54: 0 | AX54: 0
A55: 21194249 | B55: 伯希和PELLIOT 岩壳PRO 升级版时尚舒适户外运动全压胶登山服单层硬壳 徒步都市生活/旅游/通勤 防水防风透气耐磨冲锋衣 男女同款 | C55: 1124301070 | D55: 伯希和/PELLIOT | E55: 服装-外套-冲锋衣 | F55: 一品多商 | G55: 品牌直发 | H55: 0 | I55: =VLOOKUP(C55,[6]sheet1!$C:$X,6,0) -> 0 | J55: =VLOOKUP(C55,[1]sheet1!$C:$I,6,0) -> 0 | K55: =VLOOKUP(C55,[2]sheet1!$C:$H,6,0) -> 0 | L55: =VLOOKUP(C55,[3]sheet1!$C:$H,6,0) -> 0 | M55: =VLOOKUP(C55,[4]sheet1!$C:$I,6,0) -> 0 | N55: =VLOOKUP(C55,[5]sheet1!$C:$J,6,0) -> 0 | O55: =H55+I55+J55+K55+L55+M55+N55 -> 0 | P55: 0 | Q55: 0 | R55: 1025 | S55: 0 | T55: 31 | U55: 0 | V55: 0 | W55: 0 | X55: 0 | Y55: 0 | Z55: 880-890 | AA55: 805 | AB55: 754.23 | AC55: - | AD55: 0 | AE55: 0 | AF55: - | AG55: 0 | AH55: - | AI55: 689.13 | AJ55: - | AK55: 0 | AL55: - | AM55: 1179 | AN55: 0 | AO55: 0 | AP55: 0.906 | AQ55: 0.4582 | AR55: 0.7742 | AS55: 0.4516 | AT55: 0 | AU55: 0 | AV55: 0 | AW55: 0 | AX55: 0
A56: 21021042 | B56: 伯希和PELLIOT 防风防水简约修身立领舒适百搭户外城市通勤骑行耐磨休闲外套时尚保暖夹克 男款 | C56: 115151007 | D56: 伯希和/PELLIOT | E56: 服装-外套-夹克 | F56: 一品多商 | G56: 品牌直发 | H56: 0 | I56: =VLOOKUP(C56,[6]sheet1!$C:$X,6,0) -> 0 | J56: =VLOOKUP(C56,[1]sheet1!$C:$I,6,0) -> 0 | K56: =VLOOKUP(C56,[2]sheet1!$C:$H,6,0) -> 0 | L56: =VLOOKUP(C56,[3]sheet1!$C:$H,6,0) -> 0 | M56: =VLOOKUP(C56,[4]sheet1!$C:$I,6,0) -> 0 | N56: =VLOOKUP(C56,[5]sheet1!$C:$J,6,0) -> 0 | O56: =H56+I56+J56+K56+L56+M56+N56 -> 0 | P56: 0 | Q56: 0 | R56: 258 | S56: 0 | T56: 2 | U56: 0 | V56: 0 | W56: 0 | X56: 0 | Y56: 0 | Z56: 449-449 | AA56: 342 | AB56: 381.02 | AC56: - | AD56: 0 | AE56: 0 | AF56: - | AG56: 0 | AH56: - | AI56: 288.15 | AJ56: - | AK56: 0 | AL56: - | AM56: 301 | AN56: 0 | AO56: 0 | AP56: 0.6327 | AQ56: 0.4694 | AR56: 0.5 | AS56: 0.5 | AT56: 0 | AU56: 0 | AV56: 0 | AW56: 0 | AX56: 0
A57: 19870915 | B57: 伯希和PELLIOT 户外薄款透气跑步吸湿排汗抗菌修身短袖半高领柔软亲肤休闲半袖高弹面料速干专业运动T恤 男款 | C57: 115215001 | D57: 伯希和/PELLIOT | E57: 服装-上衣-T恤 | F57: 一品多商 | G57: 品牌直发 | H57: 0 | I57: =VLOOKUP(C57,[6]sheet1!$C:$X,6,0) -> 0 | J57: =VLOOKUP(C57,[1]sheet1!$C:$I,6,0) -> 0 | K57: =VLOOKUP(C57,[2]sheet1!$C:$H,6,0) -> 0 | L57: =VLOOKUP(C57,[3]sheet1!$C:$H,6,0) -> 0 | M57: =VLOOKUP(C57,[4]sheet1!$C:$I,6,0) -> 0 | N57: =VLOOKUP(C57,[5]sheet1!$C:$J,6,0) -> 0 | O57: =H57+I57+J57+K57+L57+M57+N57 -> 0 | P57: 0 | Q57: 0 | R57: 507 | S57: 0 | T57: 10 | U57: 0 | V57: 0 | W57: 0 | X57: 0 | Y57: 0 | Z57: 239-239 | AA57: 190 | AB57: 200.24 | AC57: - | AD57: 0 | AE57: 0 | AF57: - | AG57: 0 | AH57: - | AI57: 157.71 | AJ57: - | AK57: 0 | AL57: - | AM57: 573 | AN57: 0 | AO57: 0 | AP57: 0.6737 | AQ57: 0.2421 | AR57: 0.6 | AS57: 0.2 | AT57: 0 | AU57: 0 | AV57: 0 | AW57: 0 | AX57: 0
A58: 19497767 | B58: 伯希和PELLIOT 户外运动三防Teflon科技徒步登山服外套时尚宽松百搭硬壳单层专业 冲锋衣 男女同款 | C58: 115101001 | D58: 伯希和/PELLIOT | E58: 服装-外套-冲锋衣 | F58: 一品多商 | G58: 品牌直发 | H58: 0 | I58: =VLOOKUP(C58,[6]sheet1!$C:$X,6,0) -> 0 | J58: =VLOOKUP(C58,[1]sheet1!$C:$I,6,0) -> 0 | K58: =VLOOKUP(C58,[2]sheet1!$C:$H,6,0) -> 0 | L58: =VLOOKUP(C58,[3]sheet1!$C:$H,6,0) -> 0 | M58: =VLOOKUP(C58,[4]sheet1!$C:$I,6,0) -> 0 | N58: =VLOOKUP(C58,[5]sheet1!$C:$J,6,0) -> 0 | O58: =H58+I58+J58+K58+L58+M58+N58 -> 0 | P58: 0 | Q58: 0 | R58: 263 | S58: 0 | T58: 1 | U58: 0 | V58: 0 | W58: 0 | X58: 0 | Y58: 0 | Z58: 590-590 | AA58: 420 | AB58: 502.51 | AC58: - | AD58: 0 | AE58: 0 | AF58: - | AG58: 0 | AH58: - | AI58: 354.95 | AJ58: - | AK58: 0 | AL58: - | AM58: 325 | AN58: 0 | AO58: 0 | AP58: 0.8235 | AQ58: 0.451 | AR58: 1 | AS58: 1 | AT58: 0 | AU58: 0 | AV58: 0 | AW58: 0 | AX58: 0
A59: 19404505 | B59: 伯希和PELLIOT 经典2.0 轻风2.0防紫外线户外皮肤衣穿搭运动跑步轻薄透气外套防晒服 女款 | C59: 125212004 | D59: 伯希和/PELLIOT | E59: 女装-外套-防晒服 | F59: 一品多商 | G59: 品牌直发 | H59: 0 | I59: =VLOOKUP(C59,[6]sheet1!$C:$X,6,0) -> 237 | J59: =VLOOKUP(C59,[1]sheet1!$C:$I,6,0) -> 237 | K59: =VLOOKUP(C59,[2]sheet1!$C:$H,6,0) -> 0 | L59: =VLOOKUP(C59,[3]sheet1!$C:$H,6,0) -> 0 | M59: =VLOOKUP(C59,[4]sheet1!$C:$I,6,0) -> 0 | N59: =VLOOKUP(C59,[5]sheet1!$C:$J,6,0) -> 0 | O59: =H59+I59+J59+K59+L59+M59+N59 -> 474 | P59: 474 | Q59: 0 | R59: 485 | S59: 0 | T59: 6 | U59: 0 | V59: 0 | W59: 0 | X59: 0 | Y59: 0 | Z59: 229-229 | AA59: 229 | AB59: 197.65 | AC59: - | AD59: 0 | AE59: 0 | AF59: - | AG59: 0 | AH59: - | AI59: - | AJ59: - | AK59: - | AL59: - | AM59: 582 | AN59: 0 | AO59: 0 | AP59: 0.9253 | AQ59: 0.4368 | AR59: 1 | AS59: 0.5 | AT59: 0 | AU59: 0 | AV59: 0 | AW59: 0 | AX59: 0
A60: 19362667 | B60: 伯希和PELLIOT 户外3L全压胶暴雨级防水防风透气专业登山徒步运动滑雪裤硬壳百搭舒适冲锋裤 男款 | C60: 115102001 | D60: 伯希和/PELLIOT | E60: 服装-长裤-冲锋裤 | F60: 一品多商 | G60: 品牌直发 | H60: 0 | I60: =VLOOKUP(C60,[6]sheet1!$C:$X,6,0) -> 0 | J60: =VLOOKUP(C60,[1]sheet1!$C:$I,6,0) -> 0 | K60: =VLOOKUP(C60,[2]sheet1!$C:$H,6,0) -> 0 | L60: =VLOOKUP(C60,[3]sheet1!$C:$H,6,0) -> 0 | M60: =VLOOKUP(C60,[4]sheet1!$C:$I,6,0) -> 0 | N60: =VLOOKUP(C60,[5]sheet1!$C:$J,6,0) -> 0 | O60: =H60+I60+J60+K60+L60+M60+N60 -> 0 | P60: 0 | Q60: 0 | R60: 494 | S60: 0 | T60: 10 | U60: 0 | V60: 0 | W60: 0 | X60: 0 | Y60: 0 | Z60: 790-790 | AA60: 659 | AB60: 678.11 | AC60: - | AD60: 0 | AE60: 0 | AF60: - | AG60: 0 | AH60: - | AI60: 564.4 | AJ60: - | AK60: 0 | AL60: - | AM60: 532 | AN60: 0 | AO60: 0 | AP60: 0.8833 | AQ60: 0.5833 | AR60: 0.9 | AS60: 0.6 | AT60: 0 | AU60: 0 | AV60: 0 | AW60: 0 | AX60: 0
A61: 19166729 | B61: 伯希和PELLIOT MT-大师 eVent户外运动Vibram大底 防臭鞋垫舒适 减震防滑耐磨 高帮 徒步登山鞋 男款 | C61: 115119031 | D61: 伯希和/PELLIOT | E61: 鞋-运动鞋-登山鞋/徒步鞋 | F61: 一品多商 | G61: 品牌直发 | H61: 0 | I61: =VLOOKUP(C61,[6]sheet1!$C:$X,6,0) -> 0 | J61: =VLOOKUP(C61,[1]sheet1!$C:$I,6,0) -> 0 | K61: =VLOOKUP(C61,[2]sheet1!$C:$H,6,0) -> 728 | L61: =VLOOKUP(C61,[3]sheet1!$C:$H,6,0) -> 0 | M61: =VLOOKUP(C61,[4]sheet1!$C:$I,6,0) -> 728 | N61: =VLOOKUP(C61,[5]sheet1!$C:$J,6,0) -> 728 | O61: =H61+I61+J61+K61+L61+M61+N61 -> 2184 | P61: 2184 | Q61: 0 | R61: 419 | S61: 0 | T61: 6 | U61: 0 | V61: 0 | W61: 0 | X61: 0 | Y61: 0 | Z61: 689-742 | AA61: 689 | AB61: 588.95 | AC61: - | AD61: 0 | AE61: 0 | AF61: - | AG61: 0 | AH61: - | AI61: - | AJ61: - | AK61: - | AL61: - | AM61: 475 | AN61: 0 | AO61: 0 | AP61: 0.8615 | AQ61: 0.4615 | AR61: 1 | AS61: 0.3333 | AT61: 0 | AU61: 0 | AV61: 0 | AW61: 0 | AX61: 0
A62: 15773554 | B62: 伯希和PELLIOT P系列 暖盾2.0 专业Polartec200户外轻量保暖内胆摇粒绒防风舒适时尚连帽运动跑步秋季上衣卫衣抓绒衣 男款 | C62: 114310191 | D62: 伯希和/PELLIOT | E62: 服装-户外运动服-抓绒衣 | F62: 一品多商 | G62: 品牌直发 | H62: 0 | I62: =VLOOKUP(C62,[6]sheet1!$C:$X,6,0) -> 0 | J62: =VLOOKUP(C62,[1]sheet1!$C:$I,6,0) -> 0 | K62: =VLOOKUP(C62,[2]sheet1!$C:$H,6,0) -> 0 | L62: =VLOOKUP(C62,[3]sheet1!$C:$H,6,0) -> 0 | M62: =VLOOKUP(C62,[4]sheet1!$C:$I,6,0) -> 0 | N62: =VLOOKUP(C62,[5]sheet1!$C:$J,6,0) -> 0 | O62: =H62+I62+J62+K62+L62+M62+N62 -> 0 | P62: 0 | Q62: 0 | R62: 238 | S62: 0 | T62: 2 | U62: 0 | V62: 0 | W62: 0 | X62: 0 | Y62: 0 | Z62: 379-390 | AA62: 299 | AB62: 319.16 | AC62: - | AD62: 0 | AE62: 0 | AF62: - | AG62: 0 | AH62: - | AI62: 249.72 | AJ62: - | AK62: 0 | AL62: - | AM62: 283 | AN62: 0 | AO62: 0 | AP62: 0.7381 | AQ62: 0.381 | AR62: 1 | AS62: 0.5 | AT62: 0 | AU62: 0 | AV62: 0 | AW62: 0 | AX62: 0
A63: 15515666 | B63: 伯希和PELLIOT MT-山岩2.0 户外运动靴男防滑耐磨高帮爬山专业 徒步鞋 男女同款 | C63: 124419008 | D63: 伯希和/PELLIOT | E63: 鞋-运动鞋-登山鞋/徒步鞋 | F63: 一品一商 | G63: 品牌直发 | H63: 0 | I63: =VLOOKUP(C63,[6]sheet1!$C:$X,6,0) -> 0 | J63: =VLOOKUP(C63,[1]sheet1!$C:$I,6,0) -> 0 | K63: =VLOOKUP(C63,[2]sheet1!$C:$H,6,0) -> 447 | L63: =VLOOKUP(C63,[3]sheet1!$C:$H,6,0) -> 0 | M63: =VLOOKUP(C63,[4]sheet1!$C:$I,6,0) -> 0 | N63: =VLOOKUP(C63,[5]sheet1!$C:$J,6,0) -> 0 | O63: =H63+I63+J63+K63+L63+M63+N63 -> 447 | P63: 447 | Q63: 0 | R63: 97 | S63: 0 | T63: 7 | U63: 0 | V63: 0 | W63: 0 | X63: 0 | Y63: 0 | Z63: - | AA63: - | AB63: - | AC63: - | AD63: 0 | AE63: 0 | AF63: - | AG63: - | AH63: - | AI63: - | AJ63: - | AK63: - | AL63: - | AM63: 139 | AN63: 0 | AO63: 0 | AP63: 0.8557 | AQ63: 0.5155 | AR63: 0.8571 | AS63: 0.5714 | AT63: 0 | AU63: 0 | AV63: 0 | AW63: 0 | AX63: 0
A64: 14825760 | B64: 伯希和PELLIOT 伞兵裤防泼拒水时尚宽松遮肉亲肤透气阔腿裤徒步登山运动速干裤 男女同款 | C64: PE124314376 | D64: 伯希和/PELLIOT | E64: 服装-户外运动服-速干裤 | F64: 一品多商 | G64: 品牌直发 | H64: 0 | I64: =VLOOKUP(C64,[6]sheet1!$C:$X,6,0) -> 0 | J64: =VLOOKUP(C64,[1]sheet1!$C:$I,6,0) -> 0 | K64: =VLOOKUP(C64,[2]sheet1!$C:$H,6,0) -> 0 | L64: =VLOOKUP(C64,[3]sheet1!$C:$H,6,0) -> 0 | M64: =VLOOKUP(C64,[4]sheet1!$C:$I,6,0) -> 0 | N64: =VLOOKUP(C64,[5]sheet1!$C:$J,6,0) -> 0 | O64: =H64+I64+J64+K64+L64+M64+N64 -> 0 | P64: 0 | Q64: 0 | R64: 419 | S64: 0 | T64: 9 | U64: 0 | V64: 0 | W64: 0 | X64: 0 | Y64: 0 | Z64: 341-341 | AA64: 341 | AB64: 287.18 | AC64: - | AD64: 0 | AE64: 0 | AF64: - | AG64: 0 | AH64: - | AI64: - | AJ64: - | AK64: - | AL64: - | AM64: 473 | AN64: 0 | AO64: 0 | AP64: 0.7077 | AQ64: 0.2692 | AR64: 0.8889 | AS64: 0.5556 | AT64: 0 | AU64: 0 | AV64: 0 | AW64: 0 | AX64: 0
A65: 12601699 | B65: 伯希和PELLIOT 追风 户外运动三合一抓绒内胆防风防暴雨保暖耐磨徒步登山服舒适连帽外套 冲锋衣 男女同款 | C65: 114301033 | D65: 伯希和/PELLIOT | E65: 服装-外套-冲锋衣 | F65: 一品多商 | G65: 品牌直发 | H65: 0 | I65: =VLOOKUP(C65,[6]sheet1!$C:$X,6,0) -> 538 | J65: =VLOOKUP(C65,[1]sheet1!$C:$I,6,0) -> 0 | K65: =VLOOKUP(C65,[2]sheet1!$C:$H,6,0) -> 0 | L65: =VLOOKUP(C65,[3]sheet1!$C:$H,6,0) -> 0 | M65: =VLOOKUP(C65,[4]sheet1!$C:$I,6,0) -> 538 | N65: =VLOOKUP(C65,[5]sheet1!$C:$J,6,0) -> 0 | O65: =H65+I65+J65+K65+L65+M65+N65 -> 1076 | P65: 1076 | Q65: 0 | R65: 413 | S65: 0 | T65: 5 | U65: 0 | V65: 560 | W65: 1 | X65: 0 | Y65: 0 | Z65: 559-559 | AA65: 394 | AB65: 475.6 | AC65: - | AD65: 0 | AE65: 0 | AF65: - | AG65: 0 | AH65: - | AI65: 340.26 | AJ65: - | AK65: 0 | AL65: - | AM65: 496 | AN65: 0 | AO65: 0 | AP65: 0.7619 | AQ65: 0.5635 | AR65: 1 | AS65: 0.8 | AT65: 0 | AU65: 0 | AV65: 0 | AW65: 0 | AX65: 0
A66: 12593401 | B66: 伯希和PELLIOT 经典系列 原石 三合一户外防风透气防暴雨全天候多功能徒步登山服可拆卸摇粒绒内胆外套 冲锋衣 女款 | C66: 124301030 | D66: 伯希和/PELLIOT | E66: 女装-外套-冲锋衣 | F66: 一品多商 | G66: 品牌直发 | H66: 0 | I66: =VLOOKUP(C66,[6]sheet1!$C:$X,6,0) -> 1543.47 | J66: =VLOOKUP(C66,[1]sheet1!$C:$I,6,0) -> 519 | K66: =VLOOKUP(C66,[2]sheet1!$C:$H,6,0) -> 1017 | L66: =VLOOKUP(C66,[3]sheet1!$C:$H,6,0) -> 1037 | M66: =VLOOKUP(C66,[4]sheet1!$C:$I,6,0) -> 516 | N66: =VLOOKUP(C66,[5]sheet1!$C:$J,6,0) -> 1043 | O66: =H66+I66+J66+K66+L66+M66+N66 -> 5675.47 | P66: 5675.47 | Q66: 0 | R66: 572 | S66: 0 | T66: 17 | U66: 0 | V66: 0 | W66: 0 | X66: 0 | Y66: 0 | Z66: 479-479 | AA66: 431 | AB66: 404.38 | AC66: - | AD66: 0 | AE66: 0 | AF66: - | AG66: 0 | AH66: - | AI66: 362.72 | AJ66: - | AK66: 0 | AL66: - | AM66: 647 | AN66: 0 | AO66: 0 | AP66: 0.8802 | AQ66: 0.5083 | AR66: 1 | AS66: 0.4706 | AT66: 0 | AU66: 0 | AV66: 0 | AW66: 0 | AX66: 0
A67: 11815247 | B67: 伯希和PELLIOT 峰壳 单层户外运动跑步专业防暴雨防风耐磨徒步登山服外套基础百搭 冲锋衣 男女同款 | C67: 114301001 | D67: 伯希和/PELLIOT | E67: 服装-外套-冲锋衣 | F67: 一品多商 | G67: 品牌直发 | H67: 0 | I67: =VLOOKUP(C67,[6]sheet1!$C:$X,6,0) -> 0 | J67: =VLOOKUP(C67,[1]sheet1!$C:$I,6,0) -> 0 | K67: =VLOOKUP(C67,[2]sheet1!$C:$H,6,0) -> 0 | L67: =VLOOKUP(C67,[3]sheet1!$C:$H,6,0) -> 506 | M67: =VLOOKUP(C67,[4]sheet1!$C:$I,6,0) -> 0 | N67: =VLOOKUP(C67,[5]sheet1!$C:$J,6,0) -> 0 | O67: =H67+I67+J67+K67+L67+M67+N67 -> 506 | P67: 506 | Q67: 0 | R67: 470 | S67: 0 | T67: 3 | U67: 0 | V67: 0 | W67: 0 | X67: 0 | Y67: 0 | Z67: 448-448 | AA67: 394 | AB67: 379.25 | AC67: - | AD67: 0 | AE67: 0 | AF67: - | AG67: 0 | AH67: - | AI67: 332.38 | AJ67: - | AK67: 0 | AL67: - | AM67: 488 | AN67: 0 | AO67: 0 | AP67: 0.9018 | AQ67: 0.4049 | AR67: 1 | AS67: 0 | AT67: 0 | AU67: 0 | AV67: 0 | AW67: 0 | AX67: 0
A68: 11133725 | B68: 伯希和PELLIOT CORDURA面料户外登山徒步跑步攀岩高弹透气耐磨快干舒适抗皱有型百搭五分裤运动短裤 男款 | C68: 11421419 | D68: 伯希和/PELLIOT | E68: 服装-健身服-运动短裤 | F68: 一品一商 | G68: 普通现货 | H68: 0 | I68: =VLOOKUP(C68,[6]sheet1!$C:$X,6,0) -> 0 | J68: =VLOOKUP(C68,[1]sheet1!$C:$I,6,0) -> 0 | K68: =VLOOKUP(C68,[2]sheet1!$C:$H,6,0) -> 0 | L68: =VLOOKUP(C68,[3]sheet1!$C:$H,6,0) -> 0 | M68: =VLOOKUP(C68,[4]sheet1!$C:$I,6,0) -> 0 | N68: =VLOOKUP(C68,[5]sheet1!$C:$J,6,0) -> 0 | O68: =H68+I68+J68+K68+L68+M68+N68 -> 0 | P68: 0 | Q68: 0 | R68: 113 | S68: 0 | T68: 2 | U68: 0 | V68: 0 | W68: 0 | X68: 0 | Y68: 0 | Z68: - | AA68: - | AB68: - | AC68: - | AD68: 0 | AE68: 0 | AF68: - | AG68: - | AH68: - | AI68: - | AJ68: - | AK68: - | AL68: - | AM68: 160 | AN68: 0 | AO68: 0 | AP68: 0.6106 | AQ68: 0.177 | AR68: 0.5 | AS68: 0 | AT68: 0 | AU68: 0 | AV68: 0 | AW68: 0 | AX68: 0
A69: 10697844 | B69: 伯希和PELLIOT HT-轻云 户外登山鞋越野跑鞋全地形徒步鞋 时尚百搭四季款 低帮 生活休闲鞋 男女同款 | C69: 11411909 | D69: 伯希和/PELLIOT | E69: 鞋-运动鞋-登山鞋/徒步鞋 | F69: 一品多商 | G69: 品牌直发 | H69: 0 | I69: =VLOOKUP(C69,[6]sheet1!$C:$X,6,0) -> 641 | J69: =VLOOKUP(C69,[1]sheet1!$C:$I,6,0) -> 1305 | K69: =VLOOKUP(C69,[2]sheet1!$C:$H,6,0) -> 327 | L69: =VLOOKUP(C69,[3]sheet1!$C:$H,6,0) -> 327 | M69: =VLOOKUP(C69,[4]sheet1!$C:$I,6,0) -> 990 | N69: =VLOOKUP(C69,[5]sheet1!$C:$J,6,0) -> 0 | O69: =H69+I69+J69+K69+L69+M69+N69 -> 3590 | P69: 3590 | Q69: 0 | R69: 534 | S69: 0 | T69: 4 | U69: 0 | V69: 0 | W69: 0 | X69: 0 | Y69: 0 | Z69: 369-369 | AA69: 258 | AB69: 311.19 | AC69: - | AD69: 0 | AE69: 0 | AF69: - | AG69: 0 | AH69: - | AI69: 214.84 | AJ69: - | AK69: 0 | AL69: - | AM69: 607 | AN69: 0 | AO69: 0 | AP69: 0.8389 | AQ69: 0.2607 | AR69: 1 | AS69: 1 | AT69: 0 | AU69: 0 | AV69: 0 | AW69: 0 | AX69: 0
A70: 10559660 | B70: 伯希和PELLIOT 经典1.0 RT-2 溯溪鞋潮汐沙滩鞋登山徒步涉水鞋百搭凉鞋 低帮 户外功能鞋 男女同款 | C70: 12422002 | D70: 伯希和/PELLIOT | E70: 鞋-运动鞋-户外功能鞋 | F70: 一品多商 | G70: 品牌直发 | H70: 0 | I70: =VLOOKUP(C70,[6]sheet1!$C:$X,6,0) -> 0 | J70: =VLOOKUP(C70,[1]sheet1!$C:$I,6,0) -> 0 | K70: =VLOOKUP(C70,[2]sheet1!$C:$H,6,0) -> 0 | L70: =VLOOKUP(C70,[3]sheet1!$C:$H,6,0) -> 0 | M70: =VLOOKUP(C70,[4]sheet1!$C:$I,6,0) -> 0 | N70: =VLOOKUP(C70,[5]sheet1!$C:$J,6,0) -> 0 | O70: =H70+I70+J70+K70+L70+M70+N70 -> 0 | P70: 0 | Q70: 0 | R70: 411 | S70: 0 | T70: 1 | U70: 0 | V70: 0 | W70: 0 | X70: 0 | Y70: 0 | Z70: 268-268 | AA70: 204 | AB70: 223.42 | AC70: - | AD70: 0 | AE70: 0 | AF70: - | AG70: 0 | AH70: - | AI70: 167.87 | AJ70: - | AK70: 0 | AL70: - | AM70: 461 | AN70: 0 | AO70: 0 | AP70: 0.744 | AQ70: 0.184 | AR70: 1 | AS70: 1 | AT70: 0 | AU70: 0 | AV70: 0 | AW70: 0 | AX70: 0

Sheet Sheet2
A1: 11421507 | B1: =VLOOKUP(A1,[6]sheet1!$C:$W,8,0) -> 2743 | C1: =VLOOKUP(A1,[1]sheet1!$C:$W,8,0) -> 2593 | D1: =VLOOKUP(A1,[2]sheet1!$C:$J,8,0) -> 2818 | E1: =VLOOKUP(A1,[3]sheet1!$C:$J,8,0) -> 2798 | F1: =VLOOKUP(A1,[4]sheet1!$C:$K,8,0) -> 2756 | G1: =VLOOKUP(A1,[4]sheet1!$C:$M,8,0) -> 2756 | H1: =VLOOKUP(A1,sheet1!C:R,16,0) -> 3309 | I1: =B1+C1+D1+E1+F1+G1+H1 -> 19773 | J1: 19773 | L1: =VLOOKUP(A1,[6]sheet1!$C:$W,21,0) -> 35 | M1: =VLOOKUP(A1,[1]sheet1!$C:$W,21,0) -> 61 | N1: =VLOOKUP(A1,[2]sheet1!$C:$X,21,0) -> 34 | O1: =VLOOKUP(A1,[3]sheet1!$C:$X,21,0) -> 29 | P1: =VLOOKUP(A1,[4]sheet1!$C:$X,21,0) -> 58 | Q1: =VLOOKUP(A1,[5]sheet1!$C:$W,21,0) -> 46 | R1: =VLOOKUP(A1,sheet1!C:AF,29,0) -> 64 | S1: =L1+M1+N1+O1+P1+Q1+R1 -> 327 | U1: =VLOOKUP(A1,sheet1!C:Q,14,0) -> 42641.47
A2: 11421509 | B2: =VLOOKUP(A2,[6]sheet1!$C:$W,8,0) -> 1254 | C2: =VLOOKUP(A2,[1]sheet1!$C:$W,8,0) -> 1213 | D2: =VLOOKUP(A2,[2]sheet1!$C:$J,8,0) -> 1333 | E2: =VLOOKUP(A2,[3]sheet1!$C:$J,8,0) -> 1278 | F2: =VLOOKUP(A2,[4]sheet1!$C:$K,8,0) -> 1278 | G2: =VLOOKUP(A2,[4]sheet1!$C:$M,8,0) -> 1278 | H2: =VLOOKUP(A2,sheet1!C:R,16,0) -> 1187 | I2: =B2+C2+D2+E2+F2+G2+H2 -> 8821 | J2: 8821 | L2: =VLOOKUP(A2,[6]sheet1!$C:$W,21,0) -> 0 | M2: =VLOOKUP(A2,[1]sheet1!$C:$W,21,0) -> 0 | N2: =VLOOKUP(A2,[2]sheet1!$C:$X,21,0) -> 0 | O2: =VLOOKUP(A2,[3]sheet1!$C:$X,21,0) -> 0 | P2: =VLOOKUP(A2,[4]sheet1!$C:$X,21,0) -> 3 | Q2: =VLOOKUP(A2,[5]sheet1!$C:$W,21,0) -> 1 | R2: =VLOOKUP(A2,sheet1!C:AF,29,0) -> 2 | S2: =L2+M2+N2+O2+P2+Q2+R2 -> 6 | U2: =VLOOKUP(A2,sheet1!C:Q,14,0) -> 739
A3: 11421533 | B3: =VLOOKUP(A3,[6]sheet1!$C:$W,8,0) -> 2307 | C3: =VLOOKUP(A3,[1]sheet1!$C:$W,8,0) -> 2348 | D3: =VLOOKUP(A3,[2]sheet1!$C:$J,8,0) -> 2308 | E3: =VLOOKUP(A3,[3]sheet1!$C:$J,8,0) -> 2235 | F3: =VLOOKUP(A3,[4]sheet1!$C:$K,8,0) -> 2295 | G3: =VLOOKUP(A3,[4]sheet1!$C:$M,8,0) -> 2295 | H3: =VLOOKUP(A3,sheet1!C:R,16,0) -> 2362 | I3: =B3+C3+D3+E3+F3+G3+H3 -> 16150 | J3: 16150 | L3: =VLOOKUP(A3,[6]sheet1!$C:$W,21,0) -> 8 | M3: =VLOOKUP(A3,[1]sheet1!$C:$W,21,0) -> 7 | N3: =VLOOKUP(A3,[2]sheet1!$C:$X,21,0) -> 4 | O3: =VLOOKUP(A3,[3]sheet1!$C:$X,21,0) -> 7 | P3: =VLOOKUP(A3,[4]sheet1!$C:$X,21,0) -> 8 | Q3: =VLOOKUP(A3,[5]sheet1!$C:$W,21,0) -> 6 | R3: =VLOOKUP(A3,sheet1!C:AF,29,0) -> 2 | S3: =L3+M3+N3+O3+P3+Q3+R3 -> 42 | U3: =VLOOKUP(A3,sheet1!C:Q,14,0) -> 9522
A4: 115215025 | B4: =VLOOKUP(A4,[6]sheet1!$C:$W,8,0) -> 1105 | C4: =VLOOKUP(A4,[1]sheet1!$C:$W,8,0) -> 1061 | D4: =VLOOKUP(A4,[2]sheet1!$C:$J,8,0) -> 1450 | E4: =VLOOKUP(A4,[3]sheet1!$C:$J,8,0) -> 1454 | F4: =VLOOKUP(A4,[4]sheet1!$C:$K,8,0) -> 1435 | G4: =VLOOKUP(A4,[4]sheet1!$C:$M,8,0) -> 1435 | H4: =VLOOKUP(A4,sheet1!C:R,16,0) -> 1058 | I4: =B4+C4+D4+E4+F4+G4+H4 -> 8998 | J4: 8998 | L4: =VLOOKUP(A4,[6]sheet1!$C:$W,21,0) -> 0 | M4: =VLOOKUP(A4,[1]sheet1!$C:$W,21,0) -> 1 | N4: =VLOOKUP(A4,[2]sheet1!$C:$X,21,0) -> 0 | O4: =VLOOKUP(A4,[3]sheet1!$C:$X,21,0) -> 1 | P4: =VLOOKUP(A4,[4]sheet1!$C:$X,21,0) -> 1 | Q4: =VLOOKUP(A4,[5]sheet1!$C:$W,21,0) -> 0 | R4: =VLOOKUP(A4,sheet1!C:AF,29,0) -> 1 | S4: =L4+M4+N4+O4+P4+Q4+R4 -> 4 | U4: =VLOOKUP(A4,sheet1!C:Q,14,0) -> 1271
A5: 115215019 | B5: 0 | C5: =VLOOKUP(A5,[1]sheet1!$C:$W,8,0) -> #N/A | D5: =VLOOKUP(A5,[2]sheet1!$C:$J,8,0) -> #N/A | E5: =VLOOKUP(A5,[3]sheet1!$C:$J,8,0) -> #N/A | F5: =VLOOKUP(A5,[4]sheet1!$C:$K,8,0) -> #N/A | G5: =VLOOKUP(A5,[4]sheet1!$C:$M,8,0) -> #N/A | H5: =VLOOKUP(A5,sheet1!C:R,16,0) -> #N/A | I5: 0 | J5: 0 | L5: =VLOOKUP(A5,[6]sheet1!$C:$W,21,0) -> #N/A | M5: =VLOOKUP(A5,[1]sheet1!$C:$W,21,0) -> #N/A | N5: =VLOOKUP(A5,[2]sheet1!$C:$X,21,0) -> #N/A | O5: =VLOOKUP(A5,[3]sheet1!$C:$X,21,0) -> #N/A | P5: =VLOOKUP(A5,[4]sheet1!$C:$X,21,0) -> #N/A | Q5: =VLOOKUP(A5,[5]sheet1!$C:$W,21,0) -> #N/A | R5: =VLOOKUP(A5,sheet1!C:AF,29,0) -> #N/A | S5: 0 | U5: =VLOOKUP(A5,sheet1!C:Q,14,0) -> #N/A
A6: 12421534 | B6: =VLOOKUP(A6,[6]sheet1!$C:$W,8,0) -> 858 | C6: =VLOOKUP(A6,[1]sheet1!$C:$W,8,0) -> 776 | D6: =VLOOKUP(A6,[2]sheet1!$C:$J,8,0) -> 1478 | E6: =VLOOKUP(A6,[3]sheet1!$C:$J,8,0) -> 1276 | F6: =VLOOKUP(A6,[4]sheet1!$C:$K,8,0) -> 1360 | G6: =VLOOKUP(A6,[4]sheet1!$C:$M,8,0) -> 1360 | H6: =VLOOKUP(A6,sheet1!C:R,16,0) -> 874 | I6: =B6+C6+D6+E6+F6+G6+H6 -> 7982 | J6: 7982 | L6: =VLOOKUP(A6,[6]sheet1!$C:$W,21,0) -> 0 | M6: =VLOOKUP(A6,[1]sheet1!$C:$W,21,0) -> 0 | N6: =VLOOKUP(A6,[2]sheet1!$C:$X,21,0) -> 0 | O6: =VLOOKUP(A6,[3]sheet1!$C:$X,21,0) -> 0 | P6: =VLOOKUP(A6,[4]sheet1!$C:$X,21,0) -> 0 | Q6: =VLOOKUP(A6,[5]sheet1!$C:$W,21,0) -> 2 | R6: =VLOOKUP(A6,sheet1!C:AF,29,0) -> 0 | S6: =L6+M6+N6+O6+P6+Q6+R6 -> 2 | U6: =VLOOKUP(A6,sheet1!C:Q,14,0) -> 474
A7: 115316032 | B7: =VLOOKUP(A7,[6]sheet1!$C:$W,8,0) -> #N/A | C7: =VLOOKUP(A7,[1]sheet1!$C:$W,8,0) -> #N/A | D7: =VLOOKUP(A7,[2]sheet1!$C:$J,8,0) -> #N/A | E7: =VLOOKUP(A7,[3]sheet1!$C:$J,8,0) -> #N/A | F7: =VLOOKUP(A7,[4]sheet1!$C:$K,8,0) -> #N/A | G7: =VLOOKUP(A7,[4]sheet1!$C:$M,8,0) -> #N/A | H7: =VLOOKUP(A7,sheet1!C:R,16,0) -> #N/A | I7: 0 | J7: 0 | L7: =VLOOKUP(A7,[6]sheet1!$C:$W,21,0) -> #N/A | M7: =VLOOKUP(A7,[1]sheet1!$C:$W,21,0) -> #N/A | N7: =VLOOKUP(A7,[2]sheet1!$C:$X,21,0) -> #N/A | O7: =VLOOKUP(A7,[3]sheet1!$C:$X,21,0) -> #N/A | P7: =VLOOKUP(A7,[4]sheet1!$C:$X,21,0) -> #N/A | Q7: =VLOOKUP(A7,[5]sheet1!$C:$W,21,0) -> #N/A | R7: =VLOOKUP(A7,sheet1!C:AF,29,0) -> #N/A | S7: 0 | U7: =VLOOKUP(A7,sheet1!C:Q,14,0) -> #N/A
A8: 116215084 | B8: =VLOOKUP(A8,[6]sheet1!$C:$W,8,0) -> #N/A | C8: =VLOOKUP(A8,[1]sheet1!$C:$W,8,0) -> #N/A | D8: =VLOOKUP(A8,[2]sheet1!$C:$J,8,0) -> #N/A | E8: =VLOOKUP(A8,[3]sheet1!$C:$J,8,0) -> #N/A | F8: =VLOOKUP(A8,[4]sheet1!$C:$K,8,0) -> #N/A | G8: =VLOOKUP(A8,[4]sheet1!$C:$M,8,0) -> #N/A | H8: =VLOOKUP(A8,sheet1!C:R,16,0) -> #N/A | I8: 0 | J8: 0 | L8: =VLOOKUP(A8,[6]sheet1!$C:$W,21,0) -> #N/A | M8: =VLOOKUP(A8,[1]sheet1!$C:$W,21,0) -> #N/A | N8: =VLOOKUP(A8,[2]sheet1!$C:$X,21,0) -> #N/A | O8: =VLOOKUP(A8,[3]sheet1!$C:$X,21,0) -> #N/A | P8: =VLOOKUP(A8,[4]sheet1!$C:$X,21,0) -> #N/A | Q8: =VLOOKUP(A8,[5]sheet1!$C:$W,21,0) -> #N/A | R8: =VLOOKUP(A8,sheet1!C:AF,29,0) -> #N/A | S8: 0 | U8: =VLOOKUP(A8,sheet1!C:Q,14,0) -> #N/A
A9: 116214028 | B9: =VLOOKUP(A9,[6]sheet1!$C:$W,8,0) -> #N/A | C9: =VLOOKUP(A9,[1]sheet1!$C:$W,8,0) -> #N/A | D9: =VLOOKUP(A9,[2]sheet1!$C:$J,8,0) -> #N/A | E9: =VLOOKUP(A9,[3]sheet1!$C:$J,8,0) -> #N/A | F9: =VLOOKUP(A9,[4]sheet1!$C:$K,8,0) -> #N/A | G9: =VLOOKUP(A9,[4]sheet1!$C:$M,8,0) -> #N/A | H9: =VLOOKUP(A9,sheet1!C:R,16,0) -> #N/A | I9: 0 | J9: 0 | L9: =VLOOKUP(A9,[6]sheet1!$C:$W,21,0) -> #N/A | M9: =VLOOKUP(A9,[1]sheet1!$C:$W,21,0) -> #N/A | N9: =VLOOKUP(A9,[2]sheet1!$C:$X,21,0) -> #N/A | O9: =VLOOKUP(A9,[3]sheet1!$C:$X,21,0) -> #N/A | P9: =VLOOKUP(A9,[4]sheet1!$C:$X,21,0) -> #N/A | Q9: =VLOOKUP(A9,[5]sheet1!$C:$W,21,0) -> #N/A | R9: =VLOOKUP(A9,sheet1!C:AF,29,0) -> #N/A | S9: 0 | U9: 0
A10: 116214065 | B10: =VLOOKUP(A10,[6]sheet1!$C:$W,8,0) -> #N/A | C10: =VLOOKUP(A10,[1]sheet1!$C:$W,8,0) -> #N/A | D10: =VLOOKUP(A10,[2]sheet1!$C:$J,8,0) -> #N/A | E10: =VLOOKUP(A10,[3]sheet1!$C:$J,8,0) -> #N/A | F10: =VLOOKUP(A10,[4]sheet1!$C:$K,8,0) -> #N/A | G10: =VLOOKUP(A10,[4]sheet1!$C:$M,8,0) -> #N/A | H10: =VLOOKUP(A10,sheet1!C:R,16,0) -> #N/A | I10: 0 | J10: 0 | L10: =VLOOKUP(A10,[6]sheet1!$C:$W,21,0) -> #N/A | M10: =VLOOKUP(A10,[1]sheet1!$C:$W,21,0) -> #N/A | N10: =VLOOKUP(A10,[2]sheet1!$C:$X,21,0) -> #N/A | O10: =VLOOKUP(A10,[3]sheet1!$C:$X,21,0) -> #N/A | P10: =VLOOKUP(A10,[4]sheet1!$C:$X,21,0) -> #N/A | Q10: =VLOOKUP(A10,[5]sheet1!$C:$W,21,0) -> #N/A | R10: =VLOOKUP(A10,sheet1!C:AF,29,0) -> #N/A | S10: 0 | U10: 0
A11: 115214025 | B11: =VLOOKUP(A11,[6]sheet1!$C:$W,8,0) -> 697 | C11: =VLOOKUP(A11,[1]sheet1!$C:$W,8,0) -> 659 | D11: =VLOOKUP(A11,[2]sheet1!$C:$J,8,0) -> 687 | E11: =VLOOKUP(A11,[3]sheet1!$C:$J,8,0) -> 695 | F11: =VLOOKUP(A11,[4]sheet1!$C:$K,8,0) -> 660 | G11: =VLOOKUP(A11,[4]sheet1!$C:$M,8,0) -> 660 | H11: =VLOOKUP(A11,sheet1!C:R,16,0) -> 646 | I11: =B11+C11+D11+E11+F11+G11+H11 -> 4704 | J11: 4704 | L11: =VLOOKUP(A11,[6]sheet1!$C:$W,21,0) -> 4 | M11: =VLOOKUP(A11,[1]sheet1!$C:$W,21,0) -> 2 | N11: =VLOOKUP(A11,[2]sheet1!$C:$X,21,0) -> 0 | O11: =VLOOKUP(A11,[3]sheet1!$C:$X,21,0) -> 1 | P11: =VLOOKUP(A11,[4]sheet1!$C:$X,21,0) -> 2 | Q11: =VLOOKUP(A11,[5]sheet1!$C:$W,21,0) -> 2 | R11: =VLOOKUP(A11,sheet1!C:AF,29,0) -> 6 | S11: =L11+M11+N11+O11+P11+Q11+R11 -> 17 | U11: =VLOOKUP(A11,sheet1!C:Q,14,0) -> 4260
A12: 116214067 | B12: =VLOOKUP(A12,[6]sheet1!$C:$W,8,0) -> #N/A | C12: =VLOOKUP(A12,[1]sheet1!$C:$W,8,0) -> #N/A | D12: =VLOOKUP(A12,[2]sheet1!$C:$J,8,0) -> #N/A | E12: =VLOOKUP(A12,[3]sheet1!$C:$J,8,0) -> #N/A | F12: =VLOOKUP(A12,[4]sheet1!$C:$K,8,0) -> #N/A | G12: =VLOOKUP(A12,[4]sheet1!$C:$M,8,0) -> #N/A | H12: =VLOOKUP(A12,sheet1!C:R,16,0) -> #N/A | I12: 0 | J12: 0 | L12: =VLOOKUP(A12,[6]sheet1!$C:$W,21,0) -> #N/A | M12: =VLOOKUP(A12,[1]sheet1!$C:$W,21,0) -> #N/A | N12: =VLOOKUP(A12,[2]sheet1!$C:$X,21,0) -> #N/A | O12: =VLOOKUP(A12,[3]sheet1!$C:$X,21,0) -> #N/A | P12: =VLOOKUP(A12,[4]sheet1!$C:$X,21,0) -> #N/A | Q12: =VLOOKUP(A12,[5]sheet1!$C:$W,21,0) -> #N/A | R12: =VLOOKUP(A12,sheet1!C:AF,29,0) -> #N/A | S12: 0 | U12: 0
A13: 115214024 | B13: =VLOOKUP(A13,[6]sheet1!$C:$W,8,0) -> 1563 | C13: =VLOOKUP(A13,[1]sheet1!$C:$W,8,0) -> 1266 | D13: =VLOOKUP(A13,[2]sheet1!$C:$J,8,0) -> 1328 | E13: =VLOOKUP(A13,[3]sheet1!$C:$J,8,0) -> 1231 | F13: =VLOOKUP(A13,[4]sheet1!$C:$K,8,0) -> 1242 | G13: =VLOOKUP(A13,[4]sheet1!$C:$M,8,0) -> 1242 | H13: =VLOOKUP(A13,sheet1!C:R,16,0) -> 1213 | I13: =B13+C13+D13+E13+F13+G13+H13 -> 9085 | J13: 9085 | L13: =VLOOKUP(A13,[6]sheet1!$C:$W,21,0) -> 1 | M13: =VLOOKUP(A13,[1]sheet1!$C:$W,21,0) -> 11 | N13: =VLOOKUP(A13,[2]sheet1!$C:$X,21,0) -> 5 | O13: =VLOOKUP(A13,[3]sheet1!$C:$X,21,0) -> 16 | P13: =VLOOKUP(A13,[4]sheet1!$C:$X,21,0) -> 11 | Q13: =VLOOKUP(A13,[5]sheet1!$C:$W,21,0) -> 10 | R13: =VLOOKUP(A13,sheet1!C:AF,29,0) -> 6 | S13: =L13+M13+N13+O13+P13+Q13+R13 -> 60 | U13: =VLOOKUP(A13,sheet1!C:Q,14,0) -> 11730.64
A14: 11321405 | B14: =VLOOKUP(A14,[6]sheet1!$C:$W,8,0) -> 559 | C14: =VLOOKUP(A14,[1]sheet1!$C:$W,8,0) -> 515 | D14: =VLOOKUP(A14,[2]sheet1!$C:$J,8,0) -> 537 | E14: =VLOOKUP(A14,[3]sheet1!$C:$J,8,0) -> 542 | F14: =VLOOKUP(A14,[4]sheet1!$C:$K,8,0) -> 523 | G14: =VLOOKUP(A14,[4]sheet1!$C:$M,8,0) -> 523 | H14: =VLOOKUP(A14,sheet1!C:R,16,0) -> 1301 | I14: =B14+C14+D14+E14+F14+G14+H14 -> 4500 | J14: 4500 | L14: =VLOOKUP(A14,[6]sheet1!$C:$W,21,0) -> 0 | M14: =VLOOKUP(A14,[1]sheet1!$C:$W,21,0) -> 0 | N14: =VLOOKUP(A14,[2]sheet1!$C:$X,21,0) -> 0 | O14: =VLOOKUP(A14,[3]sheet1!$C:$X,21,0) -> 0 | P14: =VLOOKUP(A14,[4]sheet1!$C:$X,21,0) -> 0 | Q14: =VLOOKUP(A14,[5]sheet1!$C:$W,21,0) -> 0 | R14: =VLOOKUP(A14,sheet1!C:AF,29,0) -> 0 | S14: =L14+M14+N14+O14+P14+Q14+R14 -> 0 | U14: =VLOOKUP(A14,sheet1!C:Q,14,0) -> 0
A15: PE124314376 | B15: =VLOOKUP(A15,[6]sheet1!$C:$W,8,0) -> 377 | C15: =VLOOKUP(A15,[1]sheet1!$C:$W,8,0) -> 419 | D15: =VLOOKUP(A15,[2]sheet1!$C:$J,8,0) -> 405 | E15: =VLOOKUP(A15,[3]sheet1!$C:$J,8,0) -> 421 | F15: =VLOOKUP(A15,[4]sheet1!$C:$K,8,0) -> 382 | G15: =VLOOKUP(A15,[4]sheet1!$C:$M,8,0) -> 382 | H15: =VLOOKUP(A15,sheet1!C:R,16,0) -> 419 | I15: =B15+C15+D15+E15+F15+G15+H15 -> 2805 | J15: 2805 | L15: =VLOOKUP(A15,[6]sheet1!$C:$W,21,0) -> 0 | M15: =VLOOKUP(A15,[1]sheet1!$C:$W,21,0) -> 0 | N15: =VLOOKUP(A15,[2]sheet1!$C:$X,21,0) -> 0 | O15: =VLOOKUP(A15,[3]sheet1!$C:$X,21,0) -> 0 | P15: =VLOOKUP(A15,[4]sheet1!$C:$X,21,0) -> 0 | Q15: =VLOOKUP(A15,[5]sheet1!$C:$W,21,0) -> 0 | R15: =VLOOKUP(A15,sheet1!C:AF,29,0) -> 0 | S15: =L15+M15+N15+O15+P15+Q15+R15 -> 0 | U15: =VLOOKUP(A15,sheet1!C:Q,14,0) -> 0
A16: 11121411 | B16: =VLOOKUP(A16,[6]sheet1!$C:$W,8,0) -> 452 | C16: =VLOOKUP(A16,[1]sheet1!$C:$W,8,0) -> 401 | D16: =VLOOKUP(A16,[2]sheet1!$C:$J,8,0) -> 426 | E16: =VLOOKUP(A16,[3]sheet1!$C:$J,8,0) -> 459 | F16: =VLOOKUP(A16,[4]sheet1!$C:$K,8,0) -> 448 | G16: =VLOOKUP(A16,[4]sheet1!$C:$M,8,0) -> 448 | H16: =VLOOKUP(A16,sheet1!C:R,16,0) -> 401 | I16: =B16+C16+D16+E16+F16+G16+H16 -> 3035 | J16: 3035 | L16: =VLOOKUP(A16,[6]sheet1!$C:$W,21,0) -> 0 | M16: =VLOOKUP(A16,[1]sheet1!$C:$W,21,0) -> 0 | N16: =VLOOKUP(A16,[2]sheet1!$C:$X,21,0) -> 0 | O16: =VLOOKUP(A16,[3]sheet1!$C:$X,21,0) -> 0 | P16: =VLOOKUP(A16,[4]sheet1!$C:$X,21,0) -> 0 | Q16: =VLOOKUP(A16,[5]sheet1!$C:$W,21,0) -> 0 | R16: =VLOOKUP(A16,sheet1!C:AF,29,0) -> 0 | S16: =L16+M16+N16+O16+P16+Q16+R16 -> 0 | U16: =VLOOKUP(A16,sheet1!C:Q,14,0) -> 0
I18: 19773
